Workbook

Sheet Solver Optimizer
A1: Player | B1: Pos | C1: Team | D1: Salary | E1: Projection | F1: Value | G1: Selected | H1: Slot
A2: ='Wide Receivers (WR)'!B16 | B2: ="WR" | C2: ='Wide Receivers (WR)'!C16 | D2: ='Wide Receivers (WR)'!E16 | E2: ='Wide Receivers (WR)'!J16 | F2: ='Wide Receivers (WR)'!K16 | G2: 1 | J2: Total Projection | K2: =SUMPRODUCT(G2:G191, E2:E191)
A3: ='Wide Receivers (WR)'!B6 | B3: ="WR" | C3: ='Wide Receivers (WR)'!C6 | D3: ='Wide Receivers (WR)'!E6 | E3: ='Wide Receivers (WR)'!J6 | F3: ='Wide Receivers (WR)'!K6 | G3: 1 | J3: Total Salary | K3: =SUMPRODUCT(G2:G191, D2:D191)
A4: ='Wide Receivers (WR)'!B5 | B4: ="WR" | C4: ='Wide Receivers (WR)'!C5 | D4: ='Wide Receivers (WR)'!E5 | E4: ='Wide Receivers (WR)'!J5 | F4: ='Wide Receivers (WR)'!K5 | G4: 1 | J4: Players Selected | K4: =SUM(G2:G191)
A5: ='Quarterbacks (QB)'!B6 | B5: ="QB" | C5: ='Quarterbacks (QB)'!C6 | D5: ='Quarterbacks (QB)'!E6 | E5: ='Quarterbacks (QB)'!L6 | F5: ='Quarterbacks (QB)'!M6 | G5: 1
A6: ='Running Backs (RB)'!B18 | B6: ="RB" | C6: ='Running Backs (RB)'!C18 | D6: ='Running Backs (RB)'!E18 | E6: ='Running Backs (RB)'!K18 | F6: ='Running Backs (RB)'!L18 | G6: 1 | J6: QB | K6: =SUMIFS(G2:G190,B2:B190,"QB")
A7: ='Running Backs (RB)'!B24 | B7: ="RB" | C7: ='Running Backs (RB)'!C24 | D7: ='Running Backs (RB)'!E24 | E7: ='Running Backs (RB)'!K24 | F7: ='Running Backs (RB)'!L24 | G7: 1 | J7: RB | K7: =SUMIFS(G2:G190,B2:B190,"RB")
A8: ='Running Backs (RB)'!B34 | B8: ="RB" | C8: ='Running Backs (RB)'!C34 | D8: ='Running Backs (RB)'!E34 | E8: ='Running Backs (RB)'!K34 | F8: ='Running Backs (RB)'!L34 | G8: 1 | J8: WR | K8: =SUMIFS(G2:G190,B2:B190,"WR")
A9: ='Tight Ends (TE)'!B5 | B9: ="TE" | C9: ='Tight Ends (TE)'!C5 | D9: ='Tight Ends (TE)'!E5 | E9: ='Tight Ends (TE)'!J5 | F9: ='Tight Ends (TE)'!K5 | G9: 1 | J9: TE | K9: =SUMIFS(G2:G190,B2:B190,"TE")
A10: ='Defenses (D_ST)'!B5 | B10: ="DEF" | C10: ='Defenses (D_ST)'!C5 | D10: ='Defenses (D_ST)'!E5 | E10: ='Defenses (D_ST)'!G5 | F10: ='Defenses (D_ST)'!H5 | G10: 1 | J10: DEF | K10: =SUMIFS(G3:G191,B3:B191,"DEF")
A11: ='Running Backs (RB)'!B13 | B11: ="RB" | C11: ='Running Backs (RB)'!C13 | D11: ='Running Backs (RB)'!E13 | E11: ='Running Backs (RB)'!K13 | F11: ='Running Backs (RB)'!L13 | G11: 0
A12: ='Quarterbacks (QB)'!B12 | B12: ="QB" | C12: ='Quarterbacks (QB)'!C12 | D12: ='Quarterbacks (QB)'!E12 | E12: ='Quarterbacks (QB)'!L12 | F12: ='Quarterbacks (QB)'!M12 | G12: 0
A13: ='Running Backs (RB)'!B5 | B13: ="RB" | C13: ='Running Backs (RB)'!C5 | D13: ='Running Backs (RB)'!E5 | E13: ='Running Backs (RB)'!K5 | F13: ='Running Backs (RB)'!L5 | G13: 0
A14: ='Running Backs (RB)'!B20 | B14: ="RB" | C14: ='Running Backs (RB)'!C20 | D14: ='Running Backs (RB)'!E20 | E14: ='Running Backs (RB)'!K20 | F14: ='Running Backs (RB)'!L20 | G14: 0
A15: ='Tight Ends (TE)'!B9 | B15: ="TE" | C15: ='Tight Ends (TE)'!C9 | D15: ='Tight Ends (TE)'!E9 | E15: ='Tight Ends (TE)'!J9 | F15: ='Tight Ends (TE)'!K9 | G15: 0
A16: ='Defenses (D_ST)'!B12 | B16: ="DEF" | C16: ='Defenses (D_ST)'!C12 | D16: ='Defenses (D_ST)'!E12 | E16: ='Defenses (D_ST)'!G12 | F16: ='Defenses (D_ST)'!H12 | G16: 0
A17: ='Quarterbacks (QB)'!B5 | B17: ="QB" | C17: ='Quarterbacks (QB)'!C5 | D17: ='Quarterbacks (QB)'!E5 | E17: ='Quarterbacks (QB)'!L5 | F17: ='Quarterbacks (QB)'!M5 | G17: 0
A18: ='Wide Receivers (WR)'!B42 | B18: ="WR" | C18: ='Wide Receivers (WR)'!C42 | D18: ='Wide Receivers (WR)'!E42 | E18: ='Wide Receivers (WR)'!J42 | F18: ='Wide Receivers (WR)'!K42 | G18: 0
A19: ='Running Backs (RB)'!B22 | B19: ="RB" | C19: ='Running Backs (RB)'!C22 | D19: ='Running Backs (RB)'!E22 | E19: ='Running Backs (RB)'!K22 | F19: ='Running Backs (RB)'!L22 | G19: 0
A20: ='Wide Receivers (WR)'!B18 | B20: ="WR" | C20: ='Wide Receivers (WR)'!C18 | D20: ='Wide Receivers (WR)'!E18 | E20: ='Wide Receivers (WR)'!J18 | F20: ='Wide Receivers (WR)'!K18 | G20: 0
A21: ='Tight Ends (TE)'!B7 | B21: ="TE" | C21: ='Tight Ends (TE)'!C7 | D21: ='Tight Ends (TE)'!E7 | E21: ='Tight Ends (TE)'!J7 | F21: ='Tight Ends (TE)'!K7 | G21: 0
A22: ='Tight Ends (TE)'!B12 | B22: ="TE" | C22: ='Tight Ends (TE)'!C12 | D22: ='Tight Ends (TE)'!E12 | E22: ='Tight Ends (TE)'!J12 | F22: ='Tight Ends (TE)'!K12 | G22: 0
A23: ='Defenses (D_ST)'!B17 | B23: ="DEF" | C23: ='Defenses (D_ST)'!C17 | D23: ='Defenses (D_ST)'!E17 | E23: ='Defenses (D_ST)'!G17 | F23: ='Defenses (D_ST)'!H17 | G23: 0
A24: ='Running Backs (RB)'!B37 | B24: ="RB" | C24: ='Running Backs (RB)'!C37 | D24: ='Running Backs (RB)'!E37 | E24: ='Running Backs (RB)'!K37 | F24: ='Running Backs (RB)'!L37 | G24: 0
A25: ='Running Backs (RB)'!B46 | B25: ="RB" | C25: ='Running Backs (RB)'!C46 | D25: ='Running Backs (RB)'!E46 | E25: ='Running Backs (RB)'!K46 | F25: ='Running Backs (RB)'!L46 | G25: 0
A26: ='Wide Receivers (WR)'!B8 | B26: ="WR" | C26: ='Wide Receivers (WR)'!C8 | D26: ='Wide Receivers (WR)'!E8 | E26: ='Wide Receivers (WR)'!J8 | F26: ='Wide Receivers (WR)'!K8 | G26: 0
A27: ='Wide Receivers (WR)'!B55 | B27: ="WR" | C27: ='Wide Receivers (WR)'!C55 | D27: ='Wide Receivers (WR)'!E55 | E27: ='Wide Receivers (WR)'!J55 | F27: ='Wide Receivers (WR)'!K55 | G27: 0
A28: ='Tight Ends (TE)'!B34 | B28: ="TE" | C28: ='Tight Ends (TE)'!C34 | D28: ='Tight Ends (TE)'!E34 | E28: ='Tight Ends (TE)'!J34 | F28: ='Tight Ends (TE)'!K34 | G28: 0
A29: ='Defenses (D_ST)'!B28 | B29: ="DEF" | C29: ='Defenses (D_ST)'!C28 | D29: ='Defenses (D_ST)'!E28 | E29: ='Defenses (D_ST)'!G28 | F29: ='Defenses (D_ST)'!H28 | G29: 0
A30: ='Quarterbacks (QB)'!B7 | B30: ="QB" | C30: ='Quarterbacks (QB)'!C7 | D30: ='Quarterbacks (QB)'!E7 | E30: ='Quarterbacks (QB)'!L7 | F30: ='Quarterbacks (QB)'!M7 | G30: 0
A31: ='Quarterbacks (QB)'!B8 | B31: ="QB" | C31: ='Quarterbacks (QB)'!C8 | D31: ='Quarterbacks (QB)'!E8 | E31: ='Quarterbacks (QB)'!L8 | F31: ='Quarterbacks (QB)'!M8 | G31: 0
A32: ='Quarterbacks (QB)'!B9 | B32: ="QB" | C32: ='Quarterbacks (QB)'!C9 | D32: ='Quarterbacks (QB)'!E9 | E32: ='Quarterbacks (QB)'!L9 | F32: ='Quarterbacks (QB)'!M9 | G32: 0
A33: ='Quarterbacks (QB)'!B10 | B33: ="QB" | C33: ='Quarterbacks (QB)'!C10 | D33: ='Quarterbacks (QB)'!E10 | E33: ='Quarterbacks (QB)'!L10 | F33: ='Quarterbacks (QB)'!M10 | G33: 0
A34: ='Quarterbacks (QB)'!B11 | B34: ="QB" | C34: ='Quarterbacks (QB)'!C11 | D34: ='Quarterbacks (QB)'!E11 | E34: ='Quarterbacks (QB)'!L11 | F34: ='Quarterbacks (QB)'!M11 | G34: 0
A35: ='Quarterbacks (QB)'!B13 | B35: ="QB" | C35: ='Quarterbacks (QB)'!C13 | D35: ='Quarterbacks (QB)'!E13 | E35: ='Quarterbacks (QB)'!L13 | F35: ='Quarterbacks (QB)'!M13 | G35: 0
A36: ='Quarterbacks (QB)'!B14 | B36: ="QB" | C36: ='Quarterbacks (QB)'!C14 | D36: ='Quarterbacks (QB)'!E14 | E36: ='Quarterbacks (QB)'!L14 | F36: ='Quarterbacks (QB)'!M14 | G36: 0
A37: ='Quarterbacks (QB)'!B15 | B37: ="QB" | C37: ='Quarterbacks (QB)'!C15 | D37: ='Quarterbacks (QB)'!E15 | E37: ='Quarterbacks (QB)'!L15 | F37: ='Quarterbacks (QB)'!M15 | G37: 0
A38: ='Quarterbacks (QB)'!B16 | B38: ="QB" | C38: ='Quarterbacks (QB)'!C16 | D38: ='Quarterbacks (QB)'!E16 | E38: ='Quarterbacks (QB)'!L16 | F38: ='Quarterbacks (QB)'!M16 | G38: 0
A39: ='Quarterbacks (QB)'!B17 | B39: ="QB" | C39: ='Quarterbacks (QB)'!C17 | D39: ='Quarterbacks (QB)'!E17 | E39: ='Quarterbacks (QB)'!L17 | F39: ='Quarterbacks (QB)'!M17 | G39: 0
A40: ='Quarterbacks (QB)'!B18 | B40: ="QB" | C40: ='Quarterbacks (QB)'!C18 | D40: ='Quarterbacks (QB)'!E18 | E40: ='Quarterbacks (QB)'!L18 | F40: ='Quarterbacks (QB)'!M18 | G40: 0
A41: ='Quarterbacks (QB)'!B19 | B41: ="QB" | C41: ='Quarterbacks (QB)'!C19 | D41: ='Quarterbacks (QB)'!E19 | E41: ='Quarterbacks (QB)'!L19 | F41: ='Quarterbacks (QB)'!M19 | G41: 0
A42: ='Quarterbacks (QB)'!B20 | B42: ="QB" | C42: ='Quarterbacks (QB)'!C20 | D42: ='Quarterbacks (QB)'!E20 | E42: ='Quarterbacks (QB)'!L20 | F42: ='Quarterbacks (QB)'!M20 | G42: 0
A43: ='Quarterbacks (QB)'!B21 | B43: ="QB" | C43: ='Quarterbacks (QB)'!C21 | D43: ='Quarterbacks (QB)'!E21 | E43: ='Quarterbacks (QB)'!L21 | F43: ='Quarterbacks (QB)'!M21 | G43: 0
A44: ='Quarterbacks (QB)'!B22 | B44: ="QB" | C44: ='Quarterbacks (QB)'!C22 | D44: ='Quarterbacks (QB)'!E22 | E44: ='Quarterbacks (QB)'!L22 | F44: ='Quarterbacks (QB)'!M22 | G44: 0
A45: ='Quarterbacks (QB)'!B23 | B45: ="QB" | C45: ='Quarterbacks (QB)'!C23 | D45: ='Quarterbacks (QB)'!E23 | E45: ='Quarterbacks (QB)'!L23 | F45: ='Quarterbacks (QB)'!M23 | G45: 0
A46: ='Quarterbacks (QB)'!B24 | B46: ="QB" | C46: ='Quarterbacks (QB)'!C24 | D46: ='Quarterbacks (QB)'!E24 | E46: ='Quarterbacks (QB)'!L24 | F46: ='Quarterbacks (QB)'!M24 | G46: 0
A47: ='Quarterbacks (QB)'!B25 | B47: ="QB" | C47: ='Quarterbacks (QB)'!C25 | D47: ='Quarterbacks (QB)'!E25 | E47: ='Quarterbacks (QB)'!L25 | F47: ='Quarterbacks (QB)'!M25 | G47: 0
A48: ='Quarterbacks (QB)'!B32 | B48: ="QB" | C48: ='Quarterbacks (QB)'!C32 | D48: ='Quarterbacks (QB)'!E32 | E48: ='Quarterbacks (QB)'!L32 | F48: ='Quarterbacks (QB)'!M32 | G48: 0
A49: ='Quarterbacks (QB)'!B33 | B49: ="QB" | C49: ='Quarterbacks (QB)'!C33 | D49: ='Quarterbacks (QB)'!E33 | E49: ='Quarterbacks (QB)'!L33 | F49: ='Quarterbacks (QB)'!M33 | G49: 0
A50: ='Quarterbacks (QB)'!B48 | B50: ="QB" | C50: ='Quarterbacks (QB)'!C48 | D50: ='Quarterbacks (QB)'!E48 | E50: ='Quarterbacks (QB)'!L48 | F50: ='Quarterbacks (QB)'!M48 | G50: 0
A51: ='Running Backs (RB)'!B6 | B51: ="RB" | C51: ='Running Backs (RB)'!C6 | D51: ='Running Backs (RB)'!E6 | E51: ='Running Backs (RB)'!K6 | F51: ='Running Backs (RB)'!L6 | G51: 0
A52: ='Running Backs (RB)'!B7 | B52: ="RB" | C52: ='Running Backs (RB)'!C7 | D52: ='Running Backs (RB)'!E7 | E52: ='Running Backs (RB)'!K7 | F52: ='Running Backs (RB)'!L7 | G52: 0
A53: ='Running Backs (RB)'!B8 | B53: ="RB" | C53: ='Running Backs (RB)'!C8 | D53: ='Running Backs (RB)'!E8 | E53: ='Running Backs (RB)'!K8 | F53: ='Running Backs (RB)'!L8 | G53: 0
A54: ='Running Backs (RB)'!B9 | B54: ="RB" | C54: ='Running Backs (RB)'!C9 | D54: ='Running Backs (RB)'!E9 | E54: ='Running Backs (RB)'!K9 | F54: ='Running Backs (RB)'!L9 | G54: 0
A55: ='Running Backs (RB)'!B10 | B55: ="RB" | C55: ='Running Backs (RB)'!C10 | D55: ='Running Backs (RB)'!E10 | E55: ='Running Backs (RB)'!K10 | F55: ='Running Backs (RB)'!L10 | G55: 0
A56: ='Running Backs (RB)'!B11 | B56: ="RB" | C56: ='Running Backs (RB)'!C11 | D56: ='Running Backs (RB)'!E11 | E56: ='Running Backs (RB)'!K11 | F56: ='Running Backs (RB)'!L11 | G56: 0
A57: ='Running Backs (RB)'!B12 | B57: ="RB" | C57: ='Running Backs (RB)'!C12 | D57: ='Running Backs (RB)'!E12 | E57: ='Running Backs (RB)'!K12 | F57: ='Running Backs (RB)'!L12 | G57: 0
A58: ='Running Backs (RB)'!B14 | B58: ="RB" | C58: ='Running Backs (RB)'!C14 | D58: ='Running Backs (RB)'!E14 | E58: ='Running Backs (RB)'!K14 | F58: ='Running Backs (RB)'!L14 | G58: 0
A59: ='Running Backs (RB)'!B15 | B59: ="RB" | C59: ='Running Backs (RB)'!C15 | D59: ='Running Backs (RB)'!E15 | E59: ='Running Backs (RB)'!K15 | F59: ='Running Backs (RB)'!L15 | G59: 0
A60: ='Running Backs (RB)'!B16 | B60: ="RB" | C60: ='Running Backs (RB)'!C16 | D60: ='Running Backs (RB)'!E16 | E60: ='Running Backs (RB)'!K16 | F60: ='Running Backs (RB)'!L16 | G60: 0
A61: ='Running Backs (RB)'!B17 | B61: ="RB" | C61: ='Running Backs (RB)'!C17 | D61: ='Running Backs (RB)'!E17 | E61: ='Running Backs (RB)'!K17 | F61: ='Running Backs (RB)'!L17 | G61: 0
A62: ='Running Backs (RB)'!B19 | B62: ="RB" | C62: ='Running Backs (RB)'!C19 | D62: ='Running Backs (RB)'!E19 | E62: ='Running Backs (RB)'!K19 | F62: ='Running Backs (RB)'!L19 | G62: 0
A63: ='Running Backs (RB)'!B21 | B63: ="RB" | C63: ='Running Backs (RB)'!C21 | D63: ='Running Backs (RB)'!E21 | E63: ='Running Backs (RB)'!K21 | F63: ='Running Backs (RB)'!L21 | G63: 0
A64: ='Running Backs (RB)'!B23 | B64: ="RB" | C64: ='Running Backs (RB)'!C23 | D64: ='Running Backs (RB)'!E23 | E64: ='Running Backs (RB)'!K23 | F64: ='Running Backs (RB)'!L23 | G64: 0
A65: ='Running Backs (RB)'!B25 | B65: ="RB" | C65: ='Running Backs (RB)'!C25 | D65: ='Running Backs (RB)'!E25 | E65: ='Running Backs (RB)'!K25 | F65: ='Running Backs (RB)'!L25 | G65: 0
A66: ='Running Backs (RB)'!B26 | B66: ="RB" | C66: ='Running Backs (RB)'!C26 | D66: ='Running Backs (RB)'!E26 | E66: ='Running Backs (RB)'!K26 | F66: ='Running Backs (RB)'!L26 | G66: 0
A67: ='Running Backs (RB)'!B27 | B67: ="RB" | C67: ='Running Backs (RB)'!C27 | D67: ='Running Backs (RB)'!E27 | E67: ='Running Backs (RB)'!K27 | F67: ='Running Backs (RB)'!L27 | G67: 0
A68: ='Running Backs (RB)'!B28 | B68: ="RB" | C68: ='Running Backs (RB)'!C28 | D68: ='Running Backs (RB)'!E28 | E68: ='Running Backs (RB)'!K28 | F68: ='Running Backs (RB)'!L28 | G68: 0
A69: ='Running Backs (RB)'!B29 | B69: ="RB" | C69: ='Running Backs (RB)'!C29 | D69: ='Running Backs (RB)'!E29 | E69: ='Running Backs (RB)'!K29 | F69: ='Running Backs (RB)'!L29 | G69: 0
A70: ='Running Backs (RB)'!B30 | B70: ="RB" | C70: ='Running Backs (RB)'!C30 | D70: ='Running Backs (RB)'!E30 | E70: ='Running Backs (RB)'!K30 | F70: ='Running Backs (RB)'!L30 | G70: 0
A71: ='Running Backs (RB)'!B31 | B71: ="RB" | C71: ='Running Backs (RB)'!C31 | D71: ='Running Backs (RB)'!E31 | E71: ='Running Backs (RB)'!K31 | F71: ='Running Backs (RB)'!L31 | G71: 0
A72: ='Running Backs (RB)'!B32 | B72: ="RB" | C72: ='Running Backs (RB)'!C32 | D72: ='Running Backs (RB)'!E32 | E72: ='Running Backs (RB)'!K32 | F72: ='Running Backs (RB)'!L32 | G72: 0
A73: ='Running Backs (RB)'!B33 | B73: ="RB" | C73: ='Running Backs (RB)'!C33 | D73: ='Running Backs (RB)'!E33 | E73: ='Running Backs (RB)'!K33 | F73: ='Running Backs (RB)'!L33 | G73: 0
A74: ='Running Backs (RB)'!B35 | B74: ="RB" | C74: ='Running Backs (RB)'!C35 | D74: ='Running Backs (RB)'!E35 | E74: ='Running Backs (RB)'!K35 | F74: ='Running Backs (RB)'!L35 | G74: 0
A75: ='Running Backs (RB)'!B36 | B75: ="RB" | C75: ='Running Backs (RB)'!C36 | D75: ='Running Backs (RB)'!E36 | E75: ='Running Backs (RB)'!K36 | F75: ='Running Backs (RB)'!L36 | G75: 0
A76: ='Running Backs (RB)'!B38 | B76: ="RB" | C76: ='Running Backs (RB)'!C38 | D76: ='Running Backs (RB)'!E38 | E76: ='Running Backs (RB)'!K38 | F76: ='Running Backs (RB)'!L38 | G76: 0
A77: ='Running Backs (RB)'!B39 | B77: ="RB" | C77: ='Running Backs (RB)'!C39 | D77: ='Running Backs (RB)'!E39 | E77: ='Running Backs (RB)'!K39 | F77: ='Running Backs (RB)'!L39 | G77: 0
A78: ='Running Backs (RB)'!B40 | B78: ="RB" | C78: ='Running Backs (RB)'!C40 | D78: ='Running Backs (RB)'!E40 | E78: ='Running Backs (RB)'!K40 | F78: ='Running Backs (RB)'!L40 | G78: 0
A79: ='Running Backs (RB)'!B41 | B79: ="RB" | C79: ='Running Backs (RB)'!C41 | D79: ='Running Backs (RB)'!E41 | E79: ='Running Backs (RB)'!K41 | F79: ='Running Backs (RB)'!L41 | G79: 0
A80: ='Running Backs (RB)'!B42 | B80: ="RB" | C80: ='Running Backs (RB)'!C42 | D80: ='Running Backs (RB)'!E42 | E80: ='Running Backs (RB)'!K42 | F80: ='Running Backs (RB)'!L42 | G80: 0
A81: ='Running Backs (RB)'!B43 | B81: ="RB" | C81: ='Running Backs (RB)'!C43 | D81: ='Running Backs (RB)'!E43 | E81: ='Running Backs (RB)'!K43 | F81: ='Running Backs (RB)'!L43 | G81: 0
A82: ='Running Backs (RB)'!B44 | B82: ="RB" | C82: ='Running Backs (RB)'!C44 | D82: ='Running Backs (RB)'!E44 | E82: ='Running Backs (RB)'!K44 | F82: ='Running Backs (RB)'!L44 | G82: 0
A83: ='Running Backs (RB)'!B45 | B83: ="RB" | C83: ='Running Backs (RB)'!C45 | D83: ='Running Backs (RB)'!E45 | E83: ='Running Backs (RB)'!K45 | F83: ='Running Backs (RB)'!L45 | G83: 0
A84: ='Running Backs (RB)'!B47 | B84: ="RB" | C84: ='Running Backs (RB)'!C47 | D84: ='Running Backs (RB)'!E47 | E84: ='Running Backs (RB)'!K47 | F84: ='Running Backs (RB)'!L47 | G84: 0
A85: ='Running Backs (RB)'!B48 | B85: ="RB" | C85: ='Running Backs (RB)'!C48 | D85: ='Running Backs (RB)'!E48 | E85: ='Running Backs (RB)'!K48 | F85: ='Running Backs (RB)'!L48 | G85: 0
A86: ='Running Backs (RB)'!B49 | B86: ="RB" | C86: ='Running Backs (RB)'!C49 | D86: ='Running Backs (RB)'!E49 | E86: ='Running Backs (RB)'!K49 | F86: ='Running Backs (RB)'!L49 | G86: 0
A87: ='Running Backs (RB)'!B50 | B87: ="RB" | C87: ='Running Backs (RB)'!C50 | D87: ='Running Backs (RB)'!E50 | E87: ='Running Backs (RB)'!K50 | F87: ='Running Backs (RB)'!L50 | G87: 0
A88: ='Running Backs (RB)'!B51 | B88: ="RB" | C88: ='Running Backs (RB)'!C51 | D88: ='Running Backs (RB)'!E51 | E88: ='Running Backs (RB)'!K51 | F88: ='Running Backs (RB)'!L51 | G88: 0
A89: ='Running Backs (RB)'!B52 | B89: ="RB" | C89: ='Running Backs (RB)'!C52 | D89: ='Running Backs (RB)'!E52 | E89: ='Running Backs (RB)'!K52 | F89: ='Running Backs (RB)'!L52 | G89: 0
A90: ='Wide Receivers (WR)'!B9 | B90: ="WR" | C90: ='Wide Receivers (WR)'!C9 | D90: ='Wide Receivers (WR)'!E9 | E90: ='Wide Receivers (WR)'!J9 | F90: ='Wide Receivers (WR)'!K9 | G90: 0
A91: ='Wide Receivers (WR)'!B10 | B91: ="WR" | C91: ='Wide Receivers (WR)'!C10 | D91: ='Wide Receivers (WR)'!E10 | E91: ='Wide Receivers (WR)'!J10 | F91: ='Wide Receivers (WR)'!K10 | G91: 0
A92: ='Wide Receivers (WR)'!B11 | B92: ="WR" | C92: ='Wide Receivers (WR)'!C11 | D92: ='Wide Receivers (WR)'!E11 | E92: ='Wide Receivers (WR)'!J11 | F92: ='Wide Receivers (WR)'!K11 | G92: 0
A93: ='Wide Receivers (WR)'!B12 | B93: ="WR" | C93: ='Wide Receivers (WR)'!C12 | D93: ='Wide Receivers (WR)'!E12 | E93: ='Wide Receivers (WR)'!J12 | F93: ='Wide Receivers (WR)'!K12 | G93: 0
A94: ='Wide Receivers (WR)'!B13 | B94: ="WR" | C94: ='Wide Receivers (WR)'!C13 | D94: ='Wide Receivers (WR)'!E13 | E94: ='Wide Receivers (WR)'!J13 | F94: ='Wide Receivers (WR)'!K13 | G94: 0
A95: ='Wide Receivers (WR)'!B14 | B95: ="WR" | C95: ='Wide Receivers (WR)'!C14 | D95: ='Wide Receivers (WR)'!E14 | E95: ='Wide Receivers (WR)'!J14 | F95: ='Wide Receivers (WR)'!K14 | G95: 0
A96: ='Wide Receivers (WR)'!B15 | B96: ="WR" | C96: ='Wide Receivers (WR)'!C15 | D96: ='Wide Receivers (WR)'!E15 | E96: ='Wide Receivers (WR)'!J15 | F96: ='Wide Receivers (WR)'!K15 | G96: 0
A97: ='Wide Receivers (WR)'!B17 | B97: ="WR" | C97: ='Wide Receivers (WR)'!C17 | D97: ='Wide Receivers (WR)'!E17 | E97: ='Wide Receivers (WR)'!J17 | F97: ='Wide Receivers (WR)'!K17 | G97: 0
A98: ='Wide Receivers (WR)'!B19 | B98: ="WR" | C98: ='Wide Receivers (WR)'!C19 | D98: ='Wide Receivers (WR)'!E19 | E98: ='Wide Receivers (WR)'!J19 | F98: ='Wide Receivers (WR)'!K19 | G98: 0
A99: ='Wide Receivers (WR)'!B20 | B99: ="WR" | C99: ='Wide Receivers (WR)'!C20 | D99: ='Wide Receivers (WR)'!E20 | E99: ='Wide Receivers (WR)'!J20 | F99: ='Wide Receivers (WR)'!K20 | G99: 0
A100: ='Wide Receivers (WR)'!B21 | B100: ="WR" | C100: ='Wide Receivers (WR)'!C21 | D100: ='Wide Receivers (WR)'!E21 | E100: ='Wide Receivers (WR)'!J21 | F100: ='Wide Receivers (WR)'!K21 | G100: 0
...

Sheet Dashboard & Prop Tracker
A1: NFL Projections & Sportsbook Prop Edge Model
A2: Dynamic prop tracker linking sportsbook lines to model baselines. Formulas automatically compute value edges and Over/Under signals.
A4: Total Slate Players | D4: Top QB Projected Score | G4: Top RB Projected Score | J4: Top WR Projected Score
A5: =COUNTA('Quarterbacks (QB)'!B5:B49)+COUNTA('Running Backs (RB)'!B5:B52)+COUNTA('Wide Receivers (WR)'!B5:B137)+COUNTA('Tight Ends (TE)'!B5:B50) | D5: =MAX('Quarterbacks (QB)'!L5:L49) | G5: =MAX('Running Backs (RB)'!K5:K52) | J5: =MAX('Wide Receivers (WR)'!J5:J137)
A8: Live Sportsbook Line Edge Tracker & Signal Generator
A9: Player Name | B9: Position | C9: Metric / Prop | D9: Model Projection | E9: Sportsbook Line | F9: Edge (Yards) | G9: Recommendation | H9: Edge % | I9: Suggested Stake
A10: Josh Allen | B10: QB | C10: Pass Yds | D10: =INDEX('Quarterbacks (QB)'!F:F,MATCH(A10,'Quarterbacks (QB)'!B:B,0)) | E10: 220.5 | F10: =D10-E10 | G10: =IF(F10>0, "OVER", IF(F10<0, "UNDER", "PUSH")) | H10: =ABS(F10)/E10 | I10: =IF(ABS(F10)>=10, "2.0 Units", IF(ABS(F10)>=5, "1.0 Unit", "Pass"))
A11: Joe Burrow | B11: QB | C11: Pass Yds | D11: =INDEX('Quarterbacks (QB)'!F:F,MATCH(A11,'Quarterbacks (QB)'!B:B,0)) | E11: 258.5 | F11: =D11-E11 | G11: =IF(F11>0, "OVER", IF(F11<0, "UNDER", "PUSH")) | H11: =ABS(F11)/E11 | I11: =IF(ABS(F11)>=10, "2.0 Units", IF(ABS(F11)>=5, "1.0 Unit", "Pass"))
A12: Jahmyr Gibbs | B12: RB | C12: Scrimmage Yds | D12: =INDEX('Running Backs (RB)'!F:F,MATCH(A12,'Running Backs (RB)'!B:B,0)) | E12: 88.5 | F12: =D12-E12 | G12: =IF(F12>0, "OVER", IF(F12<0, "UNDER", "PUSH")) | H12: =ABS(F12)/E12 | I12: =IF(ABS(F12)>=10, "2.0 Units", IF(ABS(F12)>=5, "1.0 Unit", "Pass"))
A13: Jonathan Taylor | B13: RB | C13: Scrimmage Yds | D13: =INDEX('Running Backs (RB)'!F:F,MATCH(A13,'Running Backs (RB)'!B:B,0)) | E13: 95.5 | F13: =D13-E13 | G13: =IF(F13>0, "OVER", IF(F13<0, "UNDER", "PUSH")) | H13: =ABS(F13)/E13 | I13: =IF(ABS(F13)>=10, "2.0 Units", IF(ABS(F13)>=5, "1.0 Unit", "Pass"))
A14: Ja'Marr Chase | B14: WR | C14: Rec Yds | D14: =INDEX('Wide Receivers (WR)'!F:F,MATCH(A14,'Wide Receivers (WR)'!B:B,0)) | E14: 85.5 | F14: =D14-E14 | G14: =IF(F14>0, "OVER", IF(F14<0, "UNDER", "PUSH")) | H14: =ABS(F14)/E14 | I14: =IF(ABS(F14)>=10, "2.0 Units", IF(ABS(F14)>=5, "1.0 Unit", "Pass"))
A15: Amon-Ra St. Brown | B15: WR | C15: Rec Yds | D15: =INDEX('Wide Receivers (WR)'!F:F,MATCH(A15,'Wide Receivers (WR)'!B:B,0)) | E15: 79.5 | F15: =D15-E15 | G15: =IF(F15>0, "OVER", IF(F15<0, "UNDER", "PUSH")) | H15: =ABS(F15)/E15 | I15: =IF(ABS(F15)>=10, "2.0 Units", IF(ABS(F15)>=5, "1.0 Unit", "Pass"))
A16: Drake London | B16: WR | C16: Rec Yds | D16: =INDEX('Wide Receivers (WR)'!F:F,MATCH(A16,'Wide Receivers (WR)'!B:B,0)) | E16: 68.5 | F16: =D16-E16 | G16: =IF(F16>0, "OVER", IF(F16<0, "UNDER", "PUSH")) | H16: =ABS(F16)/E16 | I16: =IF(ABS(F16)>=10, "2.0 Units", IF(ABS(F16)>=5, "1.0 Unit", "Pass"))
A17: Trey McBride | B17: TE | C17: Rec Yds | D17: =INDEX('Tight Ends (TE)'!F:F,MATCH(A17,'Tight Ends (TE)'!B:B,0)) | E17: 62.5 | F17: =D17-E17 | G17: =IF(F17>0, "OVER", IF(F17<0, "UNDER", "PUSH")) | H17: =ABS(F17)/E17 | I17: =IF(ABS(F17)>=10, "2.0 Units", IF(ABS(F17)>=5, "1.0 Unit", "Pass"))
A20: Week 1 cleanup | B20: Removed inactive/out players and players outside the top-2 depth-chart role; see 'Removed Players' for the audit trail.

Sheet Quarterbacks (QB)
A1: Quarterbacks (QB) - Sportsbook Props Projection Model
A4: Rank | B4: Player Name | C4: Team | D4: Opponent | E4: Salary | F4: Pass Yds Prop | G4: Pass TD Odds | H4: Rush Yds Prop | I4: Rush TD Odds | J4: INT Prop | K4: Implied Pass TD % | L4: Implied Rush TD % | M4: Projected Score | N4: ESPN Projection | O4: Weighted Projection | P4: Value | Q4: Projected Ownership
A5: 1 | B5: Josh Allen | C5: BUF | D5: BAL | E5: 9400 | G5: -220 | I5: -135 | K5: 0.6875 | L5: 0.5745 | M5: 6.2 | N5: 31.4 | O5: 16.28 | P5: 1.73 | Q5: 0.0393
A6: 2 | B6: Jared Goff | C6: DET | D6: MIN | E6: 7800 | F6: 265.5 | G6: -136 | I6: 1750 | K6: 0.5763 | L6: 0.0541 | M6: 13.25 | N6: 23.1 | O6: 17.19 | P6: 2.2 | Q6: 0.0629
A7: 3 | B7: Joe Burrow | C7: CIN | D7: TEN | E7: 8300 | G7: -220 | I7: 600 | K7: 0.6875 | L7: 0.1429 | M7: 3.61 | N7: 31.7 | O7: 14.84 | P7: 1.79 | Q7: 0.0308
A8: 4 | B8: Drake Maye | C8: NE | D8: MIA | E8: 8200 | G8: -220 | I8: 275 | K8: 0.6875 | L8: 0.2667 | M8: 4.35 | N8: 33.1 | O8: 15.85 | P8: 1.93 | Q8: 0.0419
A9: 5 | B9: Lamar Jackson | C9: BAL | D9: BUF | E9: 8500 | G9: -220 | I9: 220 | K9: 0.6875 | L9: 0.3125 | M9: 4.62 | N9: 30.2 | O9: 14.86 | P9: 1.75 | Q9: 0.03
A10: 6 | B10: Trevor Lawrence | C10: JAC | D10: IND | E10: 7700 | G10: -220 | I10: 250 | K10: 0.6875 | L10: 0.2857 | M10: 4.46 | N10: 29.6 | O10: 14.52 | P10: 1.89 | Q10: 0.0307
A11: 7 | B11: Kirk Cousins | C11: LV | D11: NYJ | E11: 6800 | G11: -220 | I11: 1300 | K11: 0.6875 | L11: 0.0714 | M11: 3.18 | N11: 24 | O11: 11.51 | P11: 1.69 | Q11: 0.0105
A12: 8 | B12: Matthew Stafford | C12: LAR | D12: LAC | E12: 7600 | G12: -220 | I12: 1900 | K12: 0.6875 | L12: 0.05 | M12: 3.05 | N12: 24.6 | O12: 11.67 | P12: 1.54 | Q12: 0.0099
A13: 9 | B13: Dak Prescott | C13: DAL | D13: ARI | E13: 8000 | G13: -220 | I13: 400 | K13: 0.6875 | L13: 0.2 | M13: 3.95 | N13: 27.6 | O13: 13.41 | P13: 1.68 | Q13: 0.0199
A14: 10 | B14: Patrick Mahomes | C14: KC | D14: DEN | E14: 7900 | G14: -220 | I14: 450 | K14: 0.6875 | L14: 0.1818 | M14: 3.84 | N14: 19.8 | O14: 10.22 | P14: 1.29 | Q14: 0.0037
A15: 11 | B15: Michael Penix Jr. | C15: ATL | D15: TB | E15: 6900 | G15: -220 | I15: 700 | K15: 0.6875 | L15: 0.125 | M15: 3.5 | N15: 22 | O15: 10.9 | P15: 1.58 | Q15: 0.0072
A16: 12 | B16: Aaron Rodgers | C16: PIT | D16: CLE | E16: 7200 | G16: -220 | I16: 1000 | K16: 0.6875 | L16: 0.0909 | M16: 3.3 | N16: 21.8 | O16: 10.7 | P16: 1.49 | Q16: 0.006
A17: 13 | B17: Jacoby Brissett | C17: ARI | D17: DAL | E17: 7100 | G17: -220 | I17: 650 | K17: 0.6875 | L17: 0.1333 | M17: 3.55 | N17: 22.3 | O17: 11.05 | P17: 1.56 | Q17: 0.0077
A18: 14 | B18: Deshaun Watson | C18: CLE | D18: PIT | E18: 7300 | G18: -220 | I18: 400 | K18: 0.6875 | L18: 0.2 | M18: 3.95 | N18: 17.9 | O18: 9.53 | P18: 1.31 | Q18: 0.0022
... A23: 19 | B23: Tyler Huntley | C23: BAL | D23: BUF | E23: 6700 | G23: -220 | I23: 300 | K23: 0.6875 | L23: 0.25 | M23: 4.25 | N23: 0 | O23: 4.25 | P23: 0.63 | Q23: 0
A24: 20 | B24: Jake Browning | C24: LAC | D24: LAR | E24: 6000 | G24: -220 | K24: 0.6875 | L24: 0.1053 | M24: 2.75 | N24: 0 | O24: 2.75 | P24: 0.46 | Q24: 0
A25: 21 | B25: Cam Ward | C25: TEN | D25: CIN | E25: 6500 | G25: -220 | I25: 400 | K25: 0.6875 | L25: 0.2 | M25: 3.95 | N25: 15 | O25: 8.37 | P25: 1.29 | Q25: 0.0003
A26: 22 | B26: Kyler Murray | C26: MIN | D26: DET | E26: 7400 | F26: 215.5 | G26: 134 | I26: 500 | K26: 0.4274 | L26: 0.1667 | M26: 11.33 | N26: 24.1 | O26: 16.44 | P26: 2.22 | Q26: 0.056
A27: 23 | B27: Baker Mayfield | C27: TB | D27: ATL | E27: 7000 | G27: -220 | I27: 300 | K27: 0.6875 | L27: 0.25 | M27: 4.25 | N27: 22.1 | O27: 11.39 | P27: 1.63 | Q27: 0.0095
A28: 24 | B28: Daniel Jones | C28: IND | D28: JAC | E28: 6600 | G28: -220 | I28: 650 | K28: 0.6875 | L28: 0.1333 | M28: 3.55 | N28: 15.9 | O28: 8.49 | P28: 1.29 | Q28: 0.0004
A29: 25 | B29: Josh Johnson | C29: CIN | D29: TEN | E29: 6000 | G29: -220 | K29: 0.6875 | L29: 0 | M29: 2.75 | N29: 0 | O29: 2.75 | P29: 0.46 | Q29: 0
A30: 26 | B30: Carson Wentz | C30: MIN | D30: DET | E30: 6000 | G30: -220 | K30: 0.6875 | L30: 0 | M30: 2.75 | N30: 0 | O30: 2.75 | P30: 0.46 | Q30: 0
A31: 27 | B31: Jalon Daniels | C31: TB | D31: ATL | E31: 6300 | G31: -220 | K31: 0.6875 | L31: 0.1538 | M31: 2.75 | N31: 0 | O31: 2.75 | P31: 0.44 | Q31: 0
A32: 28 | B32: Dillon Gabriel | C32: CLE | D32: PIT | E32: 6000 | G32: -220 | K32: 0.6875 | L32: 0 | M32: 2.75 | N32: 0 | O32: 2.75 | P32: 0.46 | Q32: 0
A33: 29 | B33: Shane Buechele | C33: BUF | D33: BAL | E33: 6000 | G33: -220 | K33: 0.6875 | L33: 0 | M33: 2.75 | N33: 0 | O33: 2.75 | P33: 0.46 | Q33: 0
A34: 30 | B34: Tommy DeVito | C34: NE | D34: MIA | E34: 6000 | G34: -220 | K34: 0.6875 | L34: 0 | M34: 2.75 | N34: 0 | O34: 2.75 | P34: 0.46 | Q34: 0
A35: 31 | B35: Max Brosmer | C35: MIN | D35: DET | E35: 6000 | G35: -220 | K35: 0.6875 | L35: 0 | M35: 2.75 | N35: 0 | O35: 2.75 | P35: 0.46 | Q35: 0
A36: 32 | B36: Fernando Mendoza | C36: LV | D36: NYJ | E36: 6400 | G36: -220 | K36: 0.6875 | L36: 0 | M36: 2.75 | N36: 0 | O36: 2.75 | P36: 0.43 | Q36: 0
A37: 33 | B37: Stetson Bennett IV | C37: LAR | D37: LAC | E37: 6000 | G37: -220 | K37: 0.6875 | L37: 0 | M37: 2.75 | N37: 0 | O37: 2.75 | P37: 0.46 | Q37: 0
A38: 34 | B38: Jack Strand | C38: ATL | D38: TB | E38: 6000 | G38: -220 | K38: 0.6875 | L38: 0 | M38: 2.75 | N38: 0 | O38: 2.75 | P38: 0.46 | Q38: 0
A39: 35 | B39: Tua Tagovailoa | C39: ATL | D39: TB | E39: 6200 | G39: -220 | K39: 0.6875 | L39: 0.0833 | M39: 2.75 | N39: 0 | O39: 2.75 | P39: 0.44 | Q39: 0
A40: 36 | B40: Mason Rudolph | C40: PIT | D40: CLE | E40: 6000 | G40: -220 | K40: 0.6875 | L40: 0 | M40: 2.75 | N40: 0 | O40: 2.75 | P40: 0.46 | Q40: 0
... A93: 89 | B93: DJ Uiagalelei | C93: LAC | D93: KC | E93: 6000 | G93: -220 | K93: 0.6875 | L93: 0 | M93: 2.75 | N93: 0 | O93: 2.75 | P93: 0.46 | Q93: 0

Sheet Running Backs (RB)
A1: Running Backs (RB) - Sportsbook Props Projection Model
A4: Rank | B4: Player Name | C4: Team | D4: Opponent | E4: Salary | F4: Rush Yds Prop | G4: Anytime TD Odds | H4: Receptions Prop | I4: Rec Yds Prop | J4: Implied TD % | K4: Projected Score | L4: ESPN Projection | M4: Weighted Projection | N4: Value | O4: Projected Ownership
A5: 1 | B5: Jahmyr Gibbs | C5: DET | D5: MIN | E5: 9300 | F5: 84.5 | G5: -250 | H5: 4.5 | I5: 35.5 | J5: 0.7143 | K5: 18.54 | L5: 26 | M5: 21.52 | N5: 2.31 | O5: 0.4069
A6: 2 | B6: Kenneth Walker III | C6: KC | D6: DEN | E6: 9000 | G6: -125 | J6: 0.5556 | K6: 3.33 | L6: 21.4 | M6: 10.56 | N6: 1.17 | O6: 0.0386
A7: 3 | B7: Bijan Robinson | C7: ATL | D7: TB | E7: 8800 | G7: -205 | J7: 0.6721 | K7: 4.03 | L7: 20.3 | M7: 10.54 | N7: 1.2 | O7: 0.0394
A8: 4 | B8: James Cook III | C8: BUF | D8: BAL | E8: 8400 | G8: -150 | J8: 0.6 | K8: 3.6 | L8: 20.7 | M8: 10.44 | N8: 1.24 | O8: 0.0404
A9: 5 | B9: Jonathan Taylor | C9: IND | D9: JAC | E9: 8300 | G9: -167 | J9: 0.6255 | K9: 3.75 | L9: 17.1 | M9: 9.09 | N9: 1.1 | O9: 0.0241
A10: 6 | B10: Javonte Williams | C10: DAL | D10: ARI | E10: 7500 | G10: -250 | J10: 0.7143 | K10: 4.29 | L10: 21.8 | M10: 11.29 | N10: 1.51 | O10: 0.0624
A11: 7 | B11: Derrick Henry | C11: BAL | D11: BUF | E11: 8500 | G11: -205 | J11: 0.6721 | K11: 4.03 | L11: 20.9 | M11: 10.78 | N11: 1.27 | O11: 0.0448
A12: 8 | B12: Kyren Williams | C12: LAR | D12: LAC | E12: 7600 | G12: -160 | J12: 0.6154 | K12: 3.69 | L12: 18.7 | M12: 9.7 | N12: 1.28 | O12: 0.0348
A13: 9 | B13: Jaylen Warren | C13: PIT | D13: CLE | E13: 7400 | G13: -135 | J13: 0.5745 | K13: 3.45 | L13: 16.9 | M13: 8.83 | N13: 1.19 | O13: 0.0249
A14: 10 | B14: Ashton Jeanty | C14: LV | D14: NYJ | E14: 7200 | G14: -125 | J14: 0.5556 | K14: 3.33 | L14: 17 | M14: 8.8 | N14: 1.22 | O14: 0.0254
A15: 11 | B15: Bucky Irving | C15: TB | D15: ATL | E15: 7300 | G15: -130 | J15: 0.5652 | K15: 3.39 | L15: 18.7 | M15: 9.51 | N15: 1.3 | O15: 0.034
A16: 12 | B16: Ollie Gordon II | C16: MIA | D16: NE | E16: 6400 | G16: 130 | J16: 0.4348 | K16: 2.61 | L16: 15.9 | M16: 7.93 | N16: 1.24 | O16: 0.0192
A17: 13 | B17: Bhayshul Tuten | C17: JAC | D17: IND | E17: 6900 | G17: -115 | J17: 0.5349 | K17: 3.21 | L17: 16 | M17: 8.33 | N17: 1.21 | O17: 0.0215
... A24: 20 | B24: Chase Brown | C24: CIN | D24: TEN | E24: 7100 | G24: 105 | J24: 0.4878 | K24: 2.93 | L24: 17.3 | M24: 8.68 | N24: 1.22 | O24: 0.0245
A25: 21 | B25: James Conner | C25: ARI | D25: DAL | E25: 5100 | J25: 0.3846 | K25: 0 | L25: 0 | M25: 0 | N25: 0 | O25: 0.08
A26: 22 | B26: Jordan Mason | C26: MIN | D26: DET | E26: 6000 | G26: 140 | J26: 0.4167 | K26: 2.5 | L26: 10.5 | M26: 5.7 | N26: 0.95 | O26: 0.0039
A27: 23 | B27: Blake Corum | C27: LAR | D27: LAC | E27: 5900 | G27: 135 | J27: 0.4255 | K27: 2.55 | L27: 12.6 | M27: 6.57 | N27: 1.11 | O27: 0.0088
A28: 24 | B28: RJ Harvey | C28: DEN | D28: KC | E28: 5500 | G28: 180 | J28: 0.3571 | K28: 2.14 | L28: 8.6 | M28: 4.73 | N28: 0.86 | O28: 0.001
A29: 25 | B29: Jeremiyah Love | C29: ARI | D29: DAL | E29: 5900 | G29: 100 | J29: 0.5 | K29: 3 | L29: 12.4 | M29: 6.76 | N29: 1.15 | O29: 0.0102
A30: 26 | B30: Omarion Hampton | C30: LAC | D30: LAR | E30: 5800 | G30: 205 | J30: 0.3279 | K30: 1.97 | L30: 8.9 | M30: 4.74 | N30: 0.82 | O30: 0.0009
A31: 27 | B31: Brian Robinson Jr. | C31: ATL | D31: TB | E31: 5300 | G31: 300 | J31: 0.25 | K31: 1.5 | L31: 6.4 | M31: 3.46 | N31: 0.65 | O31: 0
A32: 28 | B32: Audric Estime | C32: CLE | D32: PIT | E32: 4300 | G32: 900 | J32: 0.1 | K32: 0.6 | L32: 0 | M32: 0.6 | N32: 0.14 | O32: 0
A33: 29 | B33: J.K. Dobbins | C33: DEN | D33: KC | E33: 5700 | G33: 140 | J33: 0.4167 | K33: 2.5 | L33: 6.9 | M33: 4.26 | N33: 0.75 | O33: 0.0002
A34: 30 | B34: Trey Benson | C34: ARI | D34: DAL | E34: 4000 | J34: 0.1667 | K34: 0 | L34: 0 | M34: 0 | N34: 0 | O34: 0.08
A35: 31 | B35: Jonah Coleman | C35: DEN | D35: KC | E35: 5300 | G35: 350 | J35: 0.2222 | K35: 1.33 | L35: 8.2 | M35: 4.08 | N35: 0.77 | O35: 0
A36: 32 | B36: De'Von Achane | C36: MIA | D36: NE | E36: 4000 | J36: 0.2083 | K36: 0 | L36: 0 | M36: 0 | N36: 0 | O36: 0.08
A37: 33 | B37: Kimani Vidal | C37: LAC | D37: LAR | E37: 5100 | G37: 300 | J37: 0.25 | K37: 1.5 | L37: 8.2 | M37: 4.18 | N37: 0.82 | O37: 0.0001
A38: 34 | B38: Isiah Pacheco | C38: DET | D38: MIN | E38: 4000 | J38: 0.2128 | K38: 0 | L38: 0 | M38: 0 | N38: 0 | O38: 0.08
A39: 35 | B39: Tyler Allgeier | C39: ARI | D39: DAL | E39: 5700 | G39: 170 | J39: 0.3704 | K39: 2.22 | L39: 8.5 | M39: 4.73 | N39: 0.83 | O39: 0.0009
A40: 36 | B40: Samaje Perine | C40: CIN | D40: TEN | E40: 5000 | G40: 220 | J40: 0.3125 | K40: 1.88 | L40: 7.7 | M40: 4.21 | N40: 0.84 | O40: 0.0001
A41: 37 | B41: Ty Johnson | C41: BUF | D41: BAL | E41: 5000 | G41: 450 | J41: 0.1818 | K41: 1.09 | L41: 5.7 | M41: 2.93 | N41: 0.59 | O41: 0
A42: 38 | B42: Rico Dowdle | C42: PIT | D42: CLE | E42: 5400 | G42: 270 | J42: 0.2703 | K42: 1.62 | L42: 9.5 | M42: 4.77 | N42: 0.88 | O42: 0.0011
A43: 39 | B43: TreVeyon Henderson | C43: NE | D43: MIA | E43: 5400 | G43: 260 | J43: 0.2778 | K43: 1.67 | L43: 7 | M43: 3.8 | N43: 0.7 | O43: 0
A44: 40 | B44: Keaton Mitchell | C44: LAC | D44: LAR | E44: 4900 | G44: 350 | J44: 0.2222 | K44: 1.33 | L44: 5.8 | M44: 3.12 | N44: 0.64 | O44: 0
A45: 41 | B45: Sean Tucker | C45: TB | D45: ATL | E45: 4400 | G45: 350 | J45: 0.2222 | K45: 1.33 | L45: 2.1 | M45: 1.64 | N45: 0.37 | O45: 0
A46: 42 | B46: Chris Rodriguez Jr. | C46: JAC | D46: IND | E46: 5200 | G46: 130 | J46: 0.4348 | K46: 2.61 | L46: 7.2 | M46: 4.45 | N46: 0.85 | O46: 0.0005
A47: 43 | B47: Malik Davis | C47: DAL | D47: ARI | E47: 4000 | J47: 0.16 | K47: 0 | L47: 0 | M47: 0 | N47: 0 | O47: 0.08
A48: 44 | B48: Kenny Gainwell | C48: TB | D48: ATL | E48: 5200 | G48: 300 | J48: 0.25 | K48: 1.5 | L48: 7.9 | M48: 4.06 | N48: 0.78 | O48: 0
A49: 45 | B49: Dylan Sampson | C49: CLE | D49: PIT | E49: 5200 | G49: 600 | J49: 0.1429 | K49: 0.86 | L49: 6.4 | M49: 3.07 | N49: 0.59 | O49: 0
A50: 46 | B50: Bam Knight | C50: ARI | D50: DAL | E50: 5600 | J50: =IF(OR(ISBLANK(G50), NOT(ISNUMBER(G50))), "", IF(G50 < 0, -G50 / (-G50 + 100), 100 / (G50 + 100))) | K50: 0 | L50: 0 | M50: 0 | N50: 0 | O50: 0.08
A51: 47 | B51: Justice Hill | C51: BAL | D51: BUF | E51: 4900 | G51: 600 | J51: 0.1429 | K51: 0.86 | L51: 6.4 | M51: 3.07 | N51: 0.63 | O51: 0
A52: 48 | B52: Mike Washington Jr. | C52: LV | D52: NYJ | E52: 5000 | G52: 240 | J52: 0.2941 | K52: 1.76 | L52: 7.7 | M52: 4.14 | N52: 0.83 | O52: 0.0001
A53: 49 | B53: Emmett Johnson | C53: KC | D53: DEN | E53: 5100 | G53: 700 | J53: 0.125 | K53: 0.75 | L53: 4.8 | M53: 2.37 | N53: 0.46 | O53: 0
A54: 50 | B54: Jaret Patterson | C54: CLE | D54: PIT | E54: 4000 | J54: 0.1905 | K54: 0 | L54: 0 | M54: 0 | N54: 0 | O54: 0.08
A55: 51 | B55: Raheim Sanders | C55: CLE | D55: PIT | E55: 4000 | J55: 0.1429 | K55: 0 | L55: 0 | M55: 0 | N55: 0 | O55: 0.08
A56: 52 | B56: Khalil Herbert | C56: ATL | D56: TB | E56: 4400 | J56: 0.0435 | K56: 0 | L56: 0 | M56: 0 | N56: 0 | O56: 0.08
A57: 53 | B57: Tyjae Spears | C57: TEN | D57: CIN | E57: 4800 | G57: 400 | J57: 0.2 | K57: 1.2 | L57: 6.6 | M57: 3.36 | N57: 0.7 | O57: 0
A58: 54 | B58: Ronnie Rivers | C58: LAR | D58: LAC | E58: 4000 | J58: 0.2174 | K58: 0 | L58: 0 | M58: 0 | N58: 0 | O58: 0.08
A59: 55 | B59: Tyler Badie | C59: DEN | D59: KC | E59: 4400 | J59: 0.0909 | K59: 0 | L59: 0 | M59: 0 | N59: 0 | O59: 0.08
A60: 56 | B60: Jaleel McLaughlin | C60: CLE | D60: PIT | E60: 4800 | G60: 1100 | J60: 0.0833 | K60: 0.5 | L60: 0 | M60: 0.5 | N60: 0.1 | O60: 0
A61: 57 | B61: Alec Ingold | C61: LAC | D61: LAR | E61: 4000 | J61: =IF(OR(ISBLANK(G61), NOT(ISNUMBER(G61))), "", IF(G61 < 0, -G61 / (-G61 + 100), 100 / (G61 + 100))) | K61: 0 | L61: 0 | M61: 0 | N61: 0 | O61: 0.08
A62: 58 | B62: Seth McGowan | C62: IND | D62: JAC | E62: 5300 | G62: 270 | J62: 0.2703 | K62: 1.62 | L62: 4 | M62: 2.57 | N62: 0.49 | O62: 0
A63: 59 | B63: Jerome Ford | C63: ARI | D63: DAL | E63: 4000 | J63: 0.1667 | K63: 0 | L63: 0 | M63: 0 | N63: 0 | O63: 0.08
A64: 60 | B64: Corey Kiner | C64: NE | D64: MIA | E64: 4700 | G64: 550 | J64: 0.1538 | K64: 0.92 | L64: 4.5 | M64: 2.35 | N64: 0.5 | O64: 0
A65: 61 | B65: Tyler Goodson | C65: DAL | D65: ARI | E65: 4500 | G65: 700 | J65: 0.125 | K65: 0.75 | L65: 5.5 | M65: 2.65 | N65: 0.59 | O65: 0
A66: 62 | B66: Sione Vaki | C66: DET | D66: MIN | E66: 4600 | G66: 950 | J66: 0.0952 | K66: 0.57 | L66: 3.4 | M66: 1.7 | N66: 0.37 | O66: 0
A67: 63 | B67: Isaiah Davis | C67: NYJ | D67: LV | E67: 5000 | G67: 600 | J67: 0.1429 | K67: 0.86 | L67: 0 | M67: 0.86 | N67: 0.17 | O67: 0
A68: 64 | B68: Lan Larison | C68: NE | D68: MIA | E68: 4000 | J68: 0.0357 | K68: 0 | L68: 0 | M68: 0 | N68: 0 | O68: 0.08
A69: 65 | B69: Dylan Laube | C69: LV | D69: NYJ | E69: 4400 | G69: 750 | J69: 0.1176 | K69: 0.71 | L69: 0 | M69: 0.71 | N69: 0.16 | O69: 0
A70: 66 | B70: DJ Herman | C70: MIA | D70: NE | E70: 4100 | J70: 0.0909 | K70: 0 | L70: 0 | M70: 0 | N70: 0 | O70: 0.08
A71: 67 | B71: Ray Davis | C71: BUF | D71: BAL | E71: 5000 | G71: 750 | J71: 0.1176 | K71: 0.71 | L71: 2.1 | M71: 1.26 | N71: 0.25 | O71: 0
A72: 68 | B72: DeeJay Dallas | C72: MIN | D72: DET | E72: 4500 | J72: 0.0625 | K72: 0 | L72: 0 | M72: 0 | N72: 0 | O72: 0.08
A73: 69 | B73: Kaytron Allen | C73: MIA | D73: NE | E73: 4500 | G73: 800 | J73: 0.1111 | K73: 0.67 | L73: 0 | M73: 0.67 | N73: 0.15 | O73: 0
A74: 70 | B74: Evan Hull | C74: ARI | D74: DAL | E74: 4000 | G74: 2400 | J74: 0.04 | K74: 0.24 | L74: 0 | M74: 0.24 | N74: 0.06 | O74: 0
A75: 71 | B75: Michael Carter | C75: TEN | D75: CIN | E75: 4400 | G75: 700 | J75: 0.125 | K75: 0.75 | L75: 0 | M75: 0.75 | N75: 0.17 | O75: 0
A76: 72 | B76: Ameer Abdullah | C76: JAC | D76: IND | E76: 4300 | G76: 1000 | J76: 0.0909 | K76: 0.55 | L76: 0 | M76: 0.55 | N76: 0.13 | O76: 0
A77: 73 | B77: Amar Johnson | C77: LAC | D77: LAR | E77: 4000 | J77: =IF(OR(ISBLANK(G77), NOT(ISNUMBER(G77))), "", IF(G77 < 0, -G77 / (-G77 + 100), 100 / (G77 + 100))) | K77: 0 | L77: 0 | M77: 0 | N77: 0 | O77: 0.08
A78: 74 | B78: Demond Claiborne | C78: MIN | D78: DET | E78: 4300 | G78: 700 | J78: 0.125 | K78: 0.75 | L78: 0 | M78: 0.75 | N78: 0.17 | O78: 0
A79: 75 | B79: Hunter Luepke | C79: DAL | D79: ARI | E79: 4300 | G79: 800 | J79: 0.1111 | K79: 0.67 | L79: 1.6 | M79: 1.04 | N79: 0.24 | O79: 0
A80: 76 | B80: Jaylen Wright | C80: MIA | D80: NE | E80: 5200 | G80: 450 | J80: 0.1818 | K80: 1.09 | L80: 5 | M80: 2.65 | N80: 0.51 | O80: 0
A81: 77 | B81: Emari Demercado | C81: DAL | D81: ARI | E81: 4600 | J81: 0.0294 | K81: 0 | L81: 0 | M81: 0 | N81: 0 | O81: 0.08
A82: 78 | B82: Reggie Gilliam | C82: NE | D82: MIA | E82: 4000 | J82: =IF(OR(ISBLANK(G82), NOT(ISNUMBER(G82))), "", IF(G82 < 0, -G82 / (-G82 + 100), 100 / (G82 + 100))) | K82: 0 | L82: 0 | M82: 0 | N82: 0 | O82: 0.08
A83: 79 | B83: Brashard Smith | C83: KC | D83: DEN | E83: 4200 | J83: 0.0278 | K83: 0 | L83: 0 | M83: 0 | N83: 0 | O83: 0.08
A84: 80 | B84: Nick Singleton | C84: TEN | D84: CIN | E84: 4000 | J84: 0.0179 | K84: 0 | L84: 0 | M84: 0 | N84: 0 | O84: 0.08
A85: 81 | B85: LeQuint Allen Jr. | C85: JAC | D85: IND | E85: 4200 | G85: 800 | J85: 0.1111 | K85: 0.67 | L85: 0 | M85: 0.67 | N85: 0.16 | O85: 0
A86: 82 | B86: Rasheen Ali | C86: BAL | D86: BUF | E86: 4100 | G86: 900 | J86: 0.1 | K86: 0.6 | L86: 0 | M86: 0.6 | N86: 0.15 | O86: 0
A87: 83 | B87: Frank Gore Jr. | C87: BUF | D87: BAL | E87: 4700 | J87: 0.1667 | K87: 0 | L87: 0 | M87: 0 | N87: 0 | O87: 0.08
A88: 84 | B88: Kalel Mullings | C88: TEN | D88: CIN | E88: 4000 | J88: 0.0294 | K88: 0 | L88: 0 | M88: 0 | N88: 0 | O88: 0.08
A89: 85 | B89: Owen Wright | C89: LV | D89: NYJ | E89: 4000 | J89: 0.0435 | K89: 0 | L89: 0 | M89: 0 | N89: 0 | O89: 0.08
A90: 86 | B90: Travis Homer | C90: PIT | D90: CLE | E90: 4400 | G90: 1700 | J90: 0.0556 | K90: 0.33 | L90: 0 | M90: 0.33 | N90: 0.08 | O90: 0
A91: 87 | B91: Kendall Milton | C91: CIN | D91: TEN | E91: 4000 | J91: 0.0294 | K91: 0 | L91: 0 | M91: 0 | N91: 0 | O91: 0.08
A92: 88 | B92: Adam Prentice | C92: DEN | D92: KC | E92: 4200 | G92: 1900 | J92: 0.05 | K92: 0.3 | L92: 0 | M92: 0.3 | N92: 0.07 | O92: 0
A93: 89 | B93: Tahj Brooks | C93: CIN | D93: TEN | E93: 4000 | G93: 1700 | J93: 0.0556 | K93: 0.33 | L93: 0 | M93: 0.33 | N93: 0.08 | O93: 0
A94: 90 | B94: Lew Nichols | C94: PIT | D94: CLE | E94: 4000 | G94: 2400 | J94: 0.04 | K94: 0.24 | L94: 0 | M94: 0.24 | N94: 0.06 | O94: 0
A95: 91 | B95: Michael Burton | C95: CLE | D95: PIT | E95: 4000 | G95: 2400 | J95: 0.04 | K95: 0.24 | L95: 0 | M95: 0.24 | N95: 0.06 | O95: 0
A96: 92 | B96: DJ Giddens | C96: IND | D96: JAC | E96: 4200 | G96: 2900 | J96: 0.0333 | K96: 0.2 | L96: 0 | M96: 0.2 | N96: 0.05 | O96: 0
A97: 93 | B97: Josh Williams | C97: TB | D97: ATL | E97: 4000 | J97: 0.0556 | K97: 0 | L97: 0 | M97: 0 | N97: 0 | O97: 0.08
A98: 94 | B98: Dean Connors | C98: LAR | D98: LAC | E98: 4000 | G98: 1900 | J98: 0.05 | K98: 0.3 | L98: 0 | M98: 0.3 | N98: 0.08 | O98: 0
A99: 95 | B99: Julius Chestnut | C99: TEN | D99: CIN | E99: 4000 | G99: 1700 | J99: 0.0556 | K99: 0.33 | L99: 0 | M99: 0.33 | N99: 0.08 | O99: 0
A100: 96 | B100: Eli Heidenreich | C100: PIT | D100: CLE | E100: 4000 | G100: 1700 | J100: 0.0556 | K100: 0.33 | L100: 0 | M100: 0.33 | N100: 0.08 | O100: 0
A101: 97 | B101: Jacob Saylors | C101: DET | D101: MIN | E101: 4100 | G101: 2000 | J101: 0.0476 | K101: 0.29 | L101: 0 | M101: 0.29 | N101: 0.07 | O101: 0
A102: 98 | B102: Kene Nwangwu | C102: NYJ | D102: LV | E102: 4000 | G102: 1700 | J102: 0.0556 | K102: 0.33 | L102: 0 | M102: 0.33 | N102: 0.08 | O102: 0
A103: 99 | B103: Trey Sermon | C103: ATL | D103: TB | E103: 4000 | J103: =IF(OR(ISBLANK(G103), NOT(ISNUMBER(G103))), "", IF(G103 < 0, -G103 / (-G103 + 100), 100 / (G103 + 100))) | K103: 0 | L103: 0 | M103: 0 | N103: 0 | O103: 0.08
A104: 100 | B104: Max Bredeson | C104: MIN | D104: DET | E104: 4000 | G104: 1900 | J104: 0.05 | K104: 0.3 | L104: 0 | M104: 0.3 | N104: 0.08 | O104: 0
A105: 101 | B105: Carlos Washington Jr. | C105: MIA | D105: NE | E105: 4000 | J105: =IF(OR(ISBLANK(G105), NOT(ISNUMBER(G105))), "", IF(G105 < 0, -G105 / (-G105 + 100), 100 / (G105 + 100))) | K105: 0 | L105: 0 | M105: 0 | N105: 0 | O105: 0.08
A106: 102 | B106: Lucas Scott | C106: BAL | D106: BUF | E106: 4000 | J106: =IF(OR(ISBLANK(G106), NOT(ISNUMBER(G106))), "", IF(G106 < 0, -G106 / (-G106 + 100), 100 / (G106 + 100))) | K106: 0 | L106: 0 | M106: 0 | N106: 0 | O106: 0.08
A107: 103 | B107: Myles Montgomery | C107: NE | D107: MIA | E107: 4000 | J107: =IF(OR(ISBLANK(G107), NOT(ISNUMBER(G107))), "", IF(G107 < 0, -G107 / (-G107 + 100), 100 / (G107 + 100))) | K107: 0 | L107: 0 | M107: 0 | N107: 0 | O107: 0.08
A108: 104 | B108: Israel Abanikanda | C108: DAL | D108: ARI | E108: 4000 | J108: =IF(OR(ISBLANK(G108), NOT(ISNUMBER(G108))), "", IF(G108 < 0, -G108 / (-G108 + 100), 100 / (G108 + 100))) | K108: 0 | L108: 0 | M108: 0 | N108: 0 | O108: 0.08
...

Sheet Wide Receivers (WR)
A1: Wide Receivers (WR) - Sportsbook Props Projection Model
A4: Rank | B4: Player Name | C4: Team | D4: Opponent | E4: Salary | F4: Rec Yds Prop | G4: Anytime TD Odds | H4: Receptions Prop | I4: Implied TD % | J4: Projected Score | K4: ESPN Projection | L4: Weighted Projection | M4: Value | N4: Projected Ownership
A5: 1 | B5: CeeDee Lamb | C5: DAL | D5: ARI | E5: 8900 | G5: 100 | I5: 0.5 | J5: 3 | K5: 18.9 | L5: 9.36 | M5: 1.05 | N5: 0.0608
A6: 2 | B6: Amon-Ra St. Brown | C6: DET | D6: MIN | E6: 8500 | F6: 78.5 | G6: 125 | H6: 6.5 | I6: 0.4444 | J6: 13.77 | K6: 16.3 | L6: 14.78 | M6: 1.74 | N6: 0.3334
A7: 3 | B7: Zay Flowers | C7: BAL | D7: BUF | E7: 8000 | G7: 140 | I7: 0.4167 | J7: 2.5 | K7: 19 | L7: 9.1 | M7: 1.14 | N7: 0.0625
A8: 4 | B8: Omar Cooper Jr. | C8: NYJ | D8: LV | E8: 5900 | G8: 235 | I8: 0.2985 | J8: 1.79 | K8: 9.9 | L8: 5.03 | M8: 0.85 | N8: 0.0039
A9: 5 | B9: Puka Nacua | C9: LAR | D9: LAC | E9: 9100 | G9: -135 | I9: 0.5745 | J9: 3.45 | K9: 21.2 | L9: 10.55 | M9: 1.16 | N9: 0.0932
A10: 6 | B10: Davante Adams | C10: LAR | D10: LAC | E10: 7300 | I10: 0.3846 | J10: 0 | K10: 0 | L10: 0 | M10: 0 | N10: 0.08
A11: 7 | B11: Tee Higgins | C11: CIN | D11: TEN | E11: 7100 | G11: 110 | I11: 0.4762 | J11: 2.86 | K11: 14.4 | L11: 7.47 | M11: 1.05 | N11: 0.0317
A12: 8 | B12: Parker Washington | C12: JAC | D12: IND | E12: 7200 | G12: 115 | I12: 0.4651 | J12: 2.79 | K12: 15.7 | L12: 7.95 | M12: 1.1 | N12: 0.041
A13: 9 | B13: Drake London | C13: ATL | D13: TB | E13: 7700 | G13: 115 | I13: 0.4651 | J13: 2.79 | K13: 17 | L13: 8.47 | M13: 1.1 | N13: 0.0491
A14: 10 | B14: Ja'Marr Chase | C14: CIN | D14: TEN | E14: 8700 | G14: -110 | I14: 0.5238 | J14: 3.14 | K14: 20.3 | L14: 10.01 | M14: 1.15 | N14: 0.0811
A15: 11 | B15: Tre Tucker | C15: LV | D15: NYJ | E15: 6100 | G15: 200 | I15: 0.3333 | J15: 2 | K15: 10.3 | L15: 5.32 | M15: 0.87 | N15: 0.0058
A16: 12 | B16: Jameson Williams | C16: DET | D16: MIN | E16: 6300 | F16: 50.5 | G16: 210 | H16: 3.5 | I16: 0.3226 | J16: 8.74 | K16: 10.5 | L16: 9.44 | M16: 1.5 | N16: 0.0985
A17: 13 | B17: Garrett Wilson | C17: NYJ | D17: LV | E17: 7000 | G17: 140 | I17: 0.4167 | J17: 2.5 | K17: 12.9 | L17: 6.66 | M17: 0.95 | N17: 0.0187
A18: 14 | B18: Justin Jefferson | C18: MIN | D18: DET | E18: 7900 | F18: 74.5 | G18: 180 | H18: 5.5 | I18: 0.3571 | J18: 12.34 | K18: 16.5 | L18: 14.01 | M18: 1.77 | N18: 0.3061
A19: 15 | B19: George Pickens | C19: DAL | D19: ARI | E19: 7800 | G19: 130 | I19: 0.4348 | J19: 2.61 | K19: 13 | L19: 6.77 | M19: 0.87 | N19: 0.0176
A20: 16 | B20: Tyquan Thornton | C20: KC | D20: DEN | E20: 4000 | I20: 0.3922 | J20: 0 | K20: 0 | L20: 0 | M20: 0 | N20: 0.08
A21: 17 | B21: Rashee Rice | C21: KC | D21: DEN | E21: 6900 | G21: 160 | I21: 0.3846 | J21: 2.31 | K21: 11.4 | L21: 5.94 | M21: 0.86 | N21: 0.0102
A22: 18 | B22: Keon Coleman | C22: BUF | D22: BAL | E22: 5600 | G22: 220 | I22: 0.3125 | J22: 1.88 | K22: 6.3 | L22: 3.65 | M22: 0.65 | N22: 0
A23: 19 | B23: Denzel Boston | C23: CLE | D23: PIT | E23: 5600 | G23: 250 | I23: 0.2857 | J23: 1.71 | K23: 10.9 | L23: 5.39 | M23: 0.96 | N23: 0.0072
A24: 20 | B24: Emeka Egbuka | C24: TB | D24: ATL | E24: 6000 | G24: 140 | I24: 0.4167 | J24: 2.5 | K24: 12.3 | L24: 6.42 | M24: 1.07 | N24: 0.0189
A25: 21 | B25: DK Metcalf | C25: PIT | D25: CLE | E25: 6600 | G25: 150 | I25: 0.4 | J25: 2.4 | K25: 11.6 | L25: 6.08 | M25: 0.92 | N25: 0.0124
A26: 22 | B26: Michael Wilson | C26: ARI | D26: DAL | E26: 6200 | G26: 150 | I26: 0.4 | J26: 2.4 | K26: 11.8 | L26: 6.16 | M26: 0.99 | N26: 0.0144
A27: 23 | B27: Carnell Tate | C27: TEN | D27: CIN | E27: 5900 | G27: 240 | I27: 0.2941 | J27: 1.76 | K27: 10.7 | L27: 5.34 | M27: 0.9 | N27: 0.0063
A28: 24 | B28: Caleb Douglas | C28: MIA | D28: NE | E28: 5300 | G28: 200 | I28: 0.3333 | J28: 2 | K28: 8.6 | L28: 4.64 | M28: 0.88 | N28: 0.002
A29: 25 | B29: Romeo Doubs | C29: NE | D29: MIA | E29: 5700 | I29: 0.2857 | J29: 0 | K29: 0 | L29: 0 | M29: 0 | N29: 0.08
A30: 26 | B30: Jakobi Meyers | C30: JAC | D30: IND | E30: 5900 | G30: 150 | I30: 0.4 | J30: 2.4 | K30: 10.2 | L30: 5.52 | M30: 0.94 | N30: 0.0079
A31: 27 | B31: DJ Moore | C31: BUF | D31: BAL | E31: 6700 | G31: 155 | I31: 0.3922 | J31: 2.35 | K31: 13 | L31: 6.61 | M31: 0.99 | N31: 0.019
A32: 28 | B32: Keenan Allen | C32: IND | D32: JAC | E32: 5800 | G32: 290 | I32: 0.2564 | J32: 1.54 | K32: 8.1 | L32: 4.16 | M32: 0.72 | N32: 0.0002
A33: 29 | B33: Jaylen Waddle | C33: DEN | D33: KC | E33: 6400 | G33: 210 | I33: 0.3226 | J33: 1.94 | K33: 9.7 | L33: 5.04 | M33: 0.79 | N33: 0.0036
A34: 30 | B34: DeMario Douglas | C34: NE | D34: MIA | E34: 5100 | G34: 240 | I34: 0.2941 | J34: 1.76 | K34: 9.9 | L34: 5.02 | M34: 0.98 | N34: 0.0046
A35: 31 | B35: Roman Wilson | C35: PIT | D35: CLE | E35: 4000 | I35: 0.2041 | J35: 0 | K35: 0 | L35: 0 | M35: 0 | N35: 0.08
A36: 32 | B36: Germie Bernard | C36: PIT | D36: CLE | E36: 5000 | G36: 220 | I36: 0.3125 | J36: 1.88 | K36: 9.7 | L36: 5 | M36: 1 | N36: 0.0046
A37: 33 | B37: Khalil Shakir | C37: BUF | D37: BAL | E37: 5700 | G37: 200 | I37: 0.3333 | J37: 2 | K37: 8.6 | L37: 4.64 | M37: 0.81 | N37: 0.0018
A38: 34 | B38: Malik Washington | C38: MIA | D38: NE | E38: 5500 | G38: 300 | I38: 0.25 | J38: 1.5 | K38: 9.8 | L38: 4.82 | M38: 0.88 | N38: 0.0029
A39: 35 | B39: KC Concepcion Jr. | C39: CLE | D39: PIT | E39: 5800 | G39: 235 | I39: 0.2985 | J39: 1.79 | K39: 9.3 | L39: 4.79 | M39: 0.83 | N39: 0.0025
A40: 36 | B40: Ryan Flournoy | C40: DAL | D40: ARI | E40: 5200 | G40: 250 | I40: 0.2857 | J40: 1.71 | K40: 8.4 | L40: 4.39 | M40: 0.84 | N40: 0.0009
A41: 37 | B41: Mack Hollins | C41: NE | D41: MIA | E41: 5600 | I41: 0.1538 | J41: 0 | K41: 0 | L41: 0 | M41: 0 | N41: 0.08
A42: 38 | B42: Pat Bryant | C42: DEN | D42: KC | E42: 4000 | I42: 0.3448 | J42: 0 | K42: 0 | L42: 0 | M42: 0 | N42: 0.08
A43: 39 | B43: Wan'Dale Robinson | C43: TEN | D43: CIN | E43: 5100 | G43: 350 | I43: 0.2222 | J43: 1.33 | K43: 7.8 | L43: 3.92 | M43: 0.77 | N43: 0
A44: 40 | B44: Xavier Worthy | C44: KC | D44: DEN | E44: 6100 | G44: 180 | I44: 0.3571 | J44: 2.14 | K44: 7.4 | L44: 4.25 | M44: 0.7 | N44: 0.0004
A45: 41 | B45: Ladd McConkey | C45: LAC | D45: LAR | E45: 6000 | G45: 245 | I45: 0.2899 | J45: 1.74 | K45: 9.4 | L45: 4.8 | M45: 0.8 | N45: 0.0025
A46: 42 | B46: Josh Downs | C46: IND | D46: JAC | E46: 5800 | G46: 290 | I46: 0.2564 | J46: 1.54 | K46: 7.6 | L46: 3.96 | M46: 0.68 | N46: 0
A47: 43 | B47: Jordan Addison | C47: MIN | D47: DET | E47: 5600 | F47: 38.5 | G47: 310 | H47: 3.5 | I47: 0.2439 | J47: 7.06 | K47: 9.2 | L47: 7.92 | M47: 1.41 | N47: 0.0559
A48: 44 | B48: Jahan Dotson | C48: ATL | D48: TB | E48: 5500 | G48: 400 | I48: 0.2 | J48: 1.2 | K48: 7 | L48: 3.52 | M48: 0.64 | N48: 0
A49: 45 | B49: Tre' Harris | C49: LAC | D49: LAR | E49: 5500 | G49: 230 | I49: 0.303 | J49: 1.82 | K49: 5.3 | L49: 3.21 | M49: 0.58 | N49: 0
A50: 46 | B50: Kendrick Bourne | C50: ARI | D50: DAL | E50: 5400 | G50: 250 | I50: 0.2857 | J50: 1.71 | K50: 7.3 | L50: 3.95 | M50: 0.73 | N50: 0
A51: 47 | B51: Rashod Bateman | C51: BAL | D51: BUF | E51: 5500 | G51: 400 | I51: 0.2 | J51: 1.2 | K51: 6.1 | L51: 3.16 | M51: 0.57 | N51: 0
A52: 48 | B52: Chris Godwin Jr. | C52: TB | D52: ATL | E52: 5400 | G52: 190 | I52: 0.3448 | J52: 2.07 | K52: 8.2 | L52: 4.52 | M52: 0.84 | N52: 0.0014
A53: 49 | B53: Joshua Palmer | C53: BUF | D53: BAL | E53: 4800 | G53: 240 | I53: 0.2941 | J53: 1.76 | K53: 2.5 | L53: 2.06 | M53: 0.43 | N53: 0
A54: 50 | B54: Cody White | C54: LV | D54: NYJ | E54: 4700 | G54: 800 | I54: 0.1111 | J54: 0.67 | K54: 4.6 | L54: 2.24 | M54: 0.48 | N54: 0
A55: 51 | B55: A.J. Brown | C55: NE | D55: MIA | E55: 6500 | G55: 150 | I55: 0.4 | J55: 2.4 | K55: 15.2 | L55: 7.52 | M55: 1.16 | N55: 0.0366
A56: 52 | B56: Alec Pierce | C56: IND | D56: JAC | E56: 5400 | I56: 0.2564 | J56: 0 | K56: 0 | L56: 0 | M56: 0 | N56: 0.08
A57: 53 | B57: Ted Hurst III | C57: TB | D57: ATL | E57: 4800 | G57: 260 | I57: 0.2778 | J57: 1.67 | K57: 6.4 | L57: 3.56 | M57: 0.74 | N57: 0
A58: 54 | B58: Shedrick Jackson | C58: ARI | D58: DAL | E58: 4000 | I58: 0.1961 | J58: 0 | K58: 0 | L58: 0 | M58: 0 | N58: 0.08
A59: 55 | B59: Josh Cameron | C59: JAC | D59: IND | E59: 4600 | G59: 270 | I59: 0.2703 | J59: 1.62 | K59: 5.3 | L59: 3.09 | M59: 0.67 | N59: 0
A60: 56 | B60: Chris Moore | C60: BAL | D60: BUF | E60: 4700 | I60: =IF(OR(ISBLANK(G60), NOT(ISNUMBER(G60))), "", IF(G60 < 0, -G60 / (-G60 + 100), 100 / (G60 + 100))) | J60: 0 | K60: 0 | L60: 0 | M60: 0 | N60: 0.08
A61: 57 | B61: Jack Bech | C61: LV | D61: NYJ | E61: 4500 | I61: 0.2222 | J61: 0 | K61: 0 | L61: 0 | M61: 0 | N61: 0.08
A62: 58 | B62: Courtland Sutton | C62: DEN | D62: KC | E62: 5700 | G62: 250 | I62: 0.2857 | J62: 1.71 | K62: 8.2 | L62: 4.31 | M62: 0.76 | N62: 0.0006
A63: 59 | B63: Tez Johnson | C63: TB | D63: ATL | E63: 4800 | G63: 400 | I63: 0.2 | J63: 1.2 | K63: 5 | L63: 2.72 | M63: 0.57 | N63: 0
A64: 60 | B64: Adonai Mitchell | C64: NYJ | D64: LV | E64: 4900 | G64: 400 | I64: 0.2 | J64: 1.2 | K64: 7.2 | L64: 3.6 | M64: 0.73 | N64: 0
A65: 61 | B65: Quentin Johnston | C65: LAC | D65: LAR | E65: 5100 | G65: 270 | I65: 0.2703 | J65: 1.62 | K65: 5.9 | L65: 3.33 | M65: 0.65 | N65: 0
A66: 62 | B66: Michael Pittman Jr. | C66: PIT | D66: CLE | E66: 4000 | I66: 0.2857 | J66: 0 | K66: 0 | L66: 0 | M66: 0 | N66: 0.08
A67: 63 | B67: Isaac TeSlaa | C67: DET | D67: MIN | E67: 4700 | G67: 475 | I67: 0.1739 | J67: 1.04 | K67: 5.6 | L67: 2.87 | M67: 0.61 | N67: 0
A68: 64 | B68: Konata Mumpfield | C68: LAR | D68: LAC | E68: 4800 | G68: 200 | I68: 0.3333 | J68: 2 | K68: 4.2 | L68: 2.88 | M68: 0.6 | N68: 0
A69: 65 | B69: Elic Ayomanor | C69: TEN | D69: CIN | E69: 4700 | G69: 550 | I69: 0.1538 | J69: 0.92 | K69: 4.8 | L69: 2.47 | M69: 0.53 | N69: 0
A70: 66 | B70: Isaiah Williams | C70: NYJ | D70: LV | E70: 4700 | G70: 1100 | I70: 0.0833 | J70: 0.5 | K70: 1.5 | L70: 0.9 | M70: 0.19 | N70: 0
A71: 67 | B71: Laquon Treadwell | C71: IND | D71: JAC | E71: 4900 | G71: 600 | I71: 0.1429 | J71: 0.86 | K71: 5.2 | L71: 2.59 | M71: 0.53 | N71: 0
A72: 68 | B72: Efton Chism III | C72: NE | D72: MIA | E72: 5000 | G72: 325 | I72: 0.2353 | J72: 1.41 | K72: 5.5 | L72: 3.05 | M72: 0.61 | N72: 0
A73: 69 | B73: Ja'Kobi Lane | C73: BAL | D73: BUF | E73: 4500 | G73: 350 | I73: 0.2222 | J73: 1.33 | K73: 7.5 | L73: 3.8 | M73: 0.84 | N73: 0
A74: 70 | B74: Mitch Tinsley | C74: CIN | D74: TEN | E74: 4500 | I74: 0.0714 | J74: 0 | K74: 0 | L74: 0 | M74: 0 | N74: 0.08
A75: 71 | B75: Isaiah Hodgins | C75: PIT | D75: CLE | E75: 4100 | I75: 0.0833 | J75: 0 | K75: 0 | L75: 0 | M75: 0 | N75: 0.08
A76: 72 | B76: KeAndre Lambert-Smith | C76: LAC | D76: LAR | E76: 4800 | G76: 900 | I76: 0.1 | J76: 0.6 | K76: 0 | L76: 0.6 | M76: 0.13 | N76: 0
A77: 73 | B77: Dohnte Meyers | C77: CIN | D77: TEN | E77: 4600 | G77: 300 | I77: 0.25 | J77: 1.5 | K77: 5.5 | L77: 3.1 | M77: 0.67 | N77: 0
A78: 74 | B78: Jerry Jeudy | C78: CLE | D78: PIT | E78: 5300 | G78: 550 | I78: 0.1538 | J78: 0.92 | K78: 4.4 | L78: 2.31 | M78: 0.44 | N78: 0
A79: 75 | B79: Ben Skowronek | C79: PIT | D79: CLE | E79: 4200 | G79: 800 | I79: 0.1111 | J79: 0.67 | K79: 0 | L79: 0.67 | M79: 0.16 | N79: 0
A80: 76 | B80: Brian Thomas Jr. | C80: JAC | D80: IND | E80: 5300 | G80: 325 | I80: 0.2353 | J80: 1.41 | K80: 5.2 | L80: 2.93 | M80: 0.55 | N80: 0
A81: 77 | B81: Kyle Williams | C81: NE | D81: MIA | E81: 4400 | G81: 500 | I81: 0.1667 | J81: 1 | K81: 4.4 | L81: 2.36 | M81: 0.54 | N81: 0
A82: 78 | B82: Devontez Walker | C82: BAL | D82: BUF | E82: 4300 | G82: 1100 | I82: 0.0833 | J82: 0.5 | K82: 1.7 | L82: 0.98 | M82: 0.23 | N82: 0
A83: 79 | B83: Chris Bell | C83: MIA | D83: NE | E83: 4800 | G83: 450 | I83: 0.1818 | J83: 1.09 | K83: 6.7 | L83: 3.33 | M83: 0.69 | N83: 0
A84: 80 | B84: Jared Wayne | C84: MIA | D84: NE | E84: 4400 | G84: 1700 | I84: 0.0556 | J84: 0.33 | K84: 1.5 | L84: 0.8 | M84: 0.18 | N84: 0
A85: 81 | B85: Travis Hunter | C85: JAC | D85: IND | E85: 4600 | G85: 350 | I85: 0.2222 | J85: 1.33 | K85: 2.3 | L85: 1.72 | M85: 0.37 | N85: 0
A86: 82 | B86: Tim Patrick | C86: NYJ | D86: LV | E86: 4500 | G86: 1100 | I86: 0.0833 | J86: 0.5 | K86: 0 | L86: 0.5 | M86: 0.11 | N86: 0
A87: 83 | B87: Xavier Restrepo | C87: TEN | D87: CIN | E87: 4000 | I87: 0.1429 | J87: 0 | K87: 0 | L87: 0 | M87: 0 | N87: 0.08
A88: 84 | B88: Isaiah Bond | C88: CLE | D88: PIT | E88: 4500 | G88: 1100 | I88: 0.0833 | J88: 0.5 | K88: 0 | L88: 0.5 | M88: 0.11 | N88: 0
A89: 85 | B89: Michael Bandy | C89: DEN | D89: KC | E89: 4000 | I89: 0.0476 | J89: 0 | K89: 0 | L89: 0 | M89: 0 | N89: 0.08
A90: 86 | B90: Theo Wease Jr. | C90: LAC | D90: LAR | E90: 4200 | G90: 1100 | I90: 0.0833 | J90: 0.5 | K90: 0 | L90: 0.5 | M90: 0.12 | N90: 0
A91: 87 | B91: Kevin Coleman Jr. | C91: MIA | D91: NE | E91: 4600 | G91: 800 | I91: 0.1111 | J91: 0.67 | K91: 2.1 | L91: 1.24 | M91: 0.27 | N91: 0
A92: 88 | B92: Jalen Nailor | C92: LV | D92: NYJ | E92: 4900 | G92: 500 | I92: 0.1667 | J92: 1 | K92: 6.8 | L92: 3.32 | M92: 0.68 | N92: 0
A93: 89 | B93: Calvin Ridley | C93: TEN | D93: CIN | E93: 4700 | G93: 700 | I93: 0.125 | J93: 0.75 | K93: 2.8 | L93: 1.57 | M93: 0.33 | N93: 0
A94: 90 | B94: Jalen Royals | C94: KC | D94: DEN | E94: 5200 | G94: 350 | I94: 0.2222 | J94: 1.33 | K94: 3.8 | L94: 2.32 | M94: 0.45 | N94: 0
A95: 91 | B95: Jamari Thrash | C95: LV | D95: NYJ | E95: 4300 | I95: 0.0667 | J95: 0 | K95: 0 | L95: 0 | M95: 0 | N95: 0.08
A96: 92 | B96: Reggie Virgil | C96: ARI | D96: DAL | E96: 4300 | G96: 600 | I96: 0.1429 | J96: 0.86 | K96: 3.3 | L96: 1.83 | M96: 0.43 | N96: 0
A97: 93 | B97: Jeshaun Jones | C97: MIN | D97: DET | E97: 4000 | I97: =IF(OR(ISBLANK(G97), NOT(ISNUMBER(G97))), "", IF(G97 < 0, -G97 / (-G97 + 100), 100 / (G97 + 100))) | J97: 0 | K97: 0 | L97: 0 | M97: 0 | N97: 0.08
A98: 94 | B98: KaVontae Turpin | C98: DAL | D98: ARI | E98: 4700 | G98: 550 | I98: 0.1538 | J98: 0.92 | K98: 2.4 | L98: 1.51 | M98: 0.32 | N98: 0
A99: 95 | B99: Jalen Brooks | C99: ARI | D99: DAL | E99: 4700 | I99: 0.0588 | J99: 0 | K99: 0 | L99: 0 | M99: 0 | N99: 0.08
A100: 96 | B100: Marvin Mims Jr. | C100: DEN | D100: KC | E100: 4500 | G100: 500 | I100: 0.1667 | J100: 1 | K100: 5.1 | L100: 2.64 | M100: 0.59 | N100: 0
A101: 97 | B101: Andrei Iosivas | C101: CIN | D101: TEN | E101: 4800 | I101: 0.0625 | J101: 0 | K101: 0 | L101: 0 | M101: 0 | N101: 0.08
A102: 98 | B102: Brandon Smith | C102: PIT | D102: CLE | E102: 4000 | I102: =IF(OR(ISBLANK(G102), NOT(ISNUMBER(G102))), "", IF(G102 < 0, -G102 / (-G102 + 100), 100 / (G102 + 100))) | J102: 0 | K102: 3.2 | L102: 3.2 | M102: 0.8 | N102: 0
...

Sheet Tight Ends (TE)
A1: Tight Ends (TE) - Sportsbook Props Projection Model
A4: Rank | B4: Player Name | C4: Team | D4: Opponent | E4: Salary | F4: Rec Yds Prop | G4: Anytime TD Odds | H4: Receptions Prop | I4: Implied TD % | J4: Projected Score | K4: ESPN Projection | L4: Weighted Projection | M4: Value | N4: Projected Ownership
A5: 1 | B5: Brock Bowers | C5: LV | D5: NYJ | E5: 7800 | G5: 115 | I5: 0.4651 | J5: 2.79 | K5: 14.8 | L5: 7.59 | M5: 0.97 | N5: 0.0414
A6: 2 | B6: Trey McBride | C6: ARI | D6: DAL | E6: 7300 | G6: 100 | I6: 0.5 | J6: 3 | K6: 15.6 | L6: 8.04 | M6: 1.1 | N6: 0.0559
A7: 3 | B7: Teagan Quitoriano | C7: ARI | D7: DAL | E7: 4300 | G7: 1400 | I7: 0.0667 | J7: 0.4 | K7: 0 | L7: 0.4 | M7: 0.09 | N7: 0
A8: 4 | B8: Tyler Warren | C8: IND | D8: JAC | E8: 5500 | G8: 200 | I8: 0.3333 | J8: 2 | K8: 10.2 | L8: 5.28 | M8: 0.96 | N8: 0.0142
A9: 5 | B9: Sam LaPorta | C9: DET | D9: MIN | E9: 5700 | F9: 53.5 | G9: 220 | H9: 4.5 | I9: 0.3125 | J9: 9.48 | K9: 9.8 | L9: 9.61 | M9: 1.69 | N9: 0.146
A10: 6 | B10: Mike Gesicki | C10: CIN | D10: TEN | E10: 5300 | G10: 220 | I10: 0.3125 | J10: 1.88 | K10: 5.9 | L10: 3.49 | M10: 0.66 | N10: 0.0009
A11: 7 | B11: Travis Kelce | C11: KC | D11: DEN | E11: 5400 | G11: 205 | I11: 0.3279 | J11: 1.97 | K11: 8.5 | L11: 4.58 | M11: 0.85 | N11: 0.007
A12: 8 | B12: T.J. Hockenson | C12: MIN | D12: DET | E12: 5200 | F12: 37 | G12: 300 | H12: 4.5 | I12: 0.25 | J12: 7.45 | K12: 9.8 | L12: 8.39 | M12: 1.61 | N12: 0.1016
A13: 9 | B13: Dalton Kincaid | C13: BUF | D13: BAL | E13: 5600 | G13: 180 | I13: 0.3571 | J13: 2.14 | K13: 8.1 | L13: 4.53 | M13: 0.81 | N13: 0.0063
A14: 10 | B14: Pat Freiermuth | C14: PIT | D14: CLE | E14: 5000 | G14: 280 | I14: 0.2632 | J14: 1.58 | K14: 7.9 | L14: 4.11 | M14: 0.82 | N14: 0.0039
A15: 11 | B15: Brenton Strange | C15: JAC | D15: IND | E15: 5100 | G15: 235 | I15: 0.2985 | J15: 1.79 | K15: 8.9 | L15: 4.63 | M15: 0.91 | N15: 0.008
A16: 12 | B16: Hunter Henry | C16: NE | D16: MIA | E16: 5200 | G16: 190 | I16: 0.3448 | J16: 2.07 | K16: 9.6 | L16: 5.08 | M16: 0.98 | N16: 0.0127
A17: 13 | B17: Harold Fannin Jr. | C17: CLE | D17: PIT | E17: 5500 | G17: 205 | I17: 0.3279 | J17: 1.97 | K17: 7.9 | L17: 4.34 | M17: 0.79 | N17: 0.005
A18: 14 | B18: Kyle Pitts Sr. | C18: ATL | D18: TB | E18: 5300 | G18: 220 | I18: 0.3125 | J18: 1.88 | K18: 9.3 | L18: 4.85 | M18: 0.91 | N18: 0.0098
A19: 15 | B19: Michael Mayer | C19: LV | D19: NYJ | E19: 4800 | G19: 290 | I19: 0.2564 | J19: 1.54 | K19: 6.4 | L19: 3.48 | M19: 0.73 | N19: 0.001
A20: 16 | B20: Tyler Higbee | C20: LAR | D20: LAC | E20: 4700 | G20: 180 | I20: 0.3571 | J20: 2.14 | K20: 5.8 | L20: 3.61 | M20: 0.77 | N20: 0.0015
A21: 17 | B21: Mason Taylor | C21: NYJ | D21: LV | E21: 5000 | G21: 290 | I21: 0.2564 | J21: 1.54 | K21: 7.9 | L21: 4.08 | M21: 0.82 | N21: 0.0038
A22: 18 | B22: Greg Dulcich | C22: MIA | D22: NE | E22: 5100 | G22: 300 | I22: 0.25 | J22: 1.5 | K22: 7.1 | L22: 3.74 | M22: 0.73 | N22: 0.0019
A23: 19 | B23: Darnell Washington | C23: PIT | D23: CLE | E23: 4800 | G23: 240 | I23: 0.2941 | J23: 1.76 | K23: 6 | L23: 3.46 | M23: 0.72 | N23: 0.0009
A24: 20 | B24: Ryan Miller | C24: NE | D24: MIA | E24: 4200 | I24: 0.2941 | J24: 0 | K24: 0 | L24: 0 | M24: 0 | N24: 0.08
A25: 21 | B25: Kenyon Sadiq | C25: NYJ | D25: LV | E25: 4900 | G25: 350 | I25: 0.2222 | J25: 1.33 | K25: 4.4 | L25: 2.56 | M25: 0.52 | N25: 0
A26: 22 | B26: Mark Andrews | C26: BAL | D26: BUF | E26: 5200 | G26: 220 | I26: 0.3125 | J26: 1.88 | K26: 8.7 | L26: 4.61 | M26: 0.89 | N26: 0.0076
A27: 23 | B27: Terrance Ferguson | C27: LAR | D27: LAC | E27: 4900 | I27: 0.1905 | J27: 0 | K27: 0 | L27: 0 | M27: 0 | N27: 0.08
A28: 24 | B28: Matt Hibner | C28: BAL | D28: BUF | E28: 4200 | I28: 0.1481 | J28: 0 | K28: 1.6 | L28: 1.6 | M28: 0.38 | N28: 0
A29: 25 | B29: Jake Ferguson | C29: DAL | D29: ARI | E29: 5400 | G29: 200 | I29: 0.3333 | J29: 2 | K29: 4.9 | L29: 3.16 | M29: 0.59 | N29: 0.0001
A30: 26 | B30: Eli Raridon | C30: NE | D30: MIA | E30: 4500 | G30: 190 | I30: 0.3448 | J30: 2.07 | K30: 7.2 | L30: 4.12 | M30: 0.92 | N30: 0.0046
A31: 27 | B31: David Njoku | C31: LAC | D31: LAR | E31: 4700 | I31: 0.2564 | J31: 0 | K31: 0 | L31: 0 | M31: 0 | N31: 0.08
A32: 28 | B32: Nate Adkins | C32: DEN | D32: KC | E32: 4100 | G32: 1100 | I32: 0.0833 | J32: 0.5 | K32: 0 | L32: 0.5 | M32: 0.12 | N32: 0
A33: 29 | B33: Elijah Higgins | C33: ARI | D33: DAL | E33: 4600 | G33: 550 | I33: 0.1538 | J33: 0.92 | K33: 3.8 | L33: 2.07 | M33: 0.45 | N33: 0
A34: 30 | B34: Josh Cuevas | C34: BAL | D34: BUF | E34: 4400 | G34: 800 | I34: 0.1111 | J34: 0.67 | K34: 1.6 | L34: 1.04 | M34: 0.24 | N34: 0
A35: 31 | B35: Cade Otton | C35: TB | D35: ATL | E35: 4800 | G35: 230 | I35: 0.303 | J35: 1.82 | K35: 6.4 | L35: 3.65 | M35: 0.76 | N35: 0.0016
A36: 32 | B36: Colby Parkinson | C36: LAR | D36: LAC | E36: 5100 | G36: 240 | I36: 0.2941 | J36: 1.76 | K36: 7.9 | L36: 4.22 | M36: 0.83 | N36: 0.0046
A37: 33 | B37: Oronde Gadsden II | C37: LAC | D37: LAR | E37: 5000 | G37: 500 | I37: 0.1667 | J37: 1 | K37: 3.4 | L37: 1.96 | M37: 0.39 | N37: 0
A38: 34 | B38: Evan Engram | C38: DEN | D38: KC | E38: 4900 | G38: 450 | I38: 0.1818 | J38: 1.09 | K38: 4.5 | L38: 2.45 | M38: 0.5 | N38: 0
A39: 35 | B39: Jeremy Ruckert | C39: NYJ | D39: LV | E39: 4300 | G39: 1400 | I39: 0.0667 | J39: 0.4 | K39: 0 | L39: 0.4 | M39: 0.09 | N39: 0
A40: 36 | B40: Noah Gray | C40: KC | D40: DEN | E40: 4400 | G40: 550 | I40: 0.1538 | J40: 0.92 | K40: 3.2 | L40: 1.83 | M40: 0.42 | N40: 0
A41: 37 | B41: Davis Allen | C41: LAR | D41: LAC | E41: 4400 | G41: 240 | I41: 0.2941 | J41: 1.76 | K41: 4.3 | L41: 2.78 | M41: 0.63 | N41: 0
A42: 38 | B42: Drew Sample | C42: CIN | D42: TEN | E42: 4500 | G42: 300 | I42: 0.25 | J42: 1.5 | K42: 2.2 | L42: 1.78 | M42: 0.4 | N42: 0
A43: 39 | B43: Austin Hooper | C43: ATL | D43: TB | E43: 4600 | G43: 800 | I43: 0.1111 | J43: 0.67 | K43: 1.8 | L43: 1.12 | M43: 0.24 | N43: 0
A44: 40 | B44: Tanner Hudson | C44: CIN | D44: TEN | E44: 4200 | I44: 0.1818 | J44: 0 | K44: 0 | L44: 0 | M44: 0 | N44: 0.08
A45: 41 | B45: Ian Thomas | C45: LV | D45: NYJ | E45: 4200 | G45: 1300 | I45: 0.0714 | J45: 0.43 | K45: 1 | L45: 0.66 | M45: 0.16 | N45: 0
A46: 42 | B46: Nate Boerkircher | C46: JAC | D46: IND | E46: 4300 | G46: 550 | I46: 0.1538 | J46: 0.92 | K46: 2.6 | L46: 1.59 | M46: 0.37 | N46: 0
A47: 43 | B47: Mo Alie-Cox | C47: IND | D47: JAC | E47: 4500 | G47: 750 | I47: 0.1176 | J47: 0.71 | K47: 0 | L47: 0.71 | M47: 0.16 | N47: 0
A48: 44 | B48: Gunnar Helm | C48: TEN | D48: CIN | E48: 4500 | G48: 500 | I48: 0.1667 | J48: 1 | K48: 3.8 | L48: 2.12 | M48: 0.47 | N48: 0
A49: 45 | B49: Charlie Kolar | C49: LAC | D49: LAR | E49: 4600 | G49: 400 | I49: 0.2 | J49: 1.2 | K49: 4 | L49: 2.32 | M49: 0.5 | N49: 0
A50: 46 | B50: Erick All Jr. | C50: CIN | D50: TEN | E50: 4400 | G50: 600 | I50: 0.1429 | J50: 0.86 | K50: 4 | L50: 2.11 | M50: 0.48 | N50: 0
A51: 47 | B51: Hayden Rucci | C51: LAC | D51: LAR | E51: 4000 | G51: 1400 | I51: 0.0667 | J51: 0.4 | K51: 0 | L51: 0.4 | M51: 0.1 | N51: 0
A52: 48 | B52: Blake Whiteheart | C52: CLE | D52: PIT | E52: 4300 | G52: 1100 | I52: 0.0833 | J52: 0.5 | K52: 0 | L52: 0.5 | M52: 0.12 | N52: 0
A53: 49 | B53: Dawson Knox | C53: BUF | D53: BAL | E53: 4700 | G53: 500 | I53: 0.1667 | J53: 1 | K53: 3.2 | L53: 1.88 | M53: 0.4 | N53: 0
A54: 50 | B54: Gavin Bartholomew | C54: MIN | D54: DET | E54: 4300 | G54: 1750 | I54: 0.0541 | J54: 0.32 | K54: 2.2 | L54: 1.07 | M54: 0.25 | N54: 0
A55: 51 | B55: Julian Hill | C55: NE | D55: MIA | E55: 4000 | I55: 0.16 | J55: 0 | K55: 0 | L55: 0 | M55: 0 | N55: 0.08
A56: 52 | B56: Josh Oliver | C56: MIN | D56: DET | E56: 4000 | I56: 0.0769 | J56: 0 | K56: 0 | L56: 0 | M56: 0 | N56: 0.08
A57: 53 | B57: Tanner Conner | C57: NE | D57: MIA | E57: 4000 | I57: 0.0323 | J57: 0 | K57: 0 | L57: 0 | M57: 0 | N57: 0.08
A58: 54 | B58: John FitzPatrick | C58: CLE | D58: PIT | E58: 4000 | I58: 0.0278 | J58: 0 | K58: 0 | L58: 0 | M58: 0 | N58: 0.08
A59: 55 | B59: Brevyn Spann-Ford | C59: DAL | D59: ARI | E59: 4200 | G59: 350 | I59: 0.2222 | J59: 1.33 | K59: 2.9 | L59: 1.96 | M59: 0.47 | N59: 0
A60: 56 | B60: Luke Schoonmaker | C60: DAL | D60: ARI | E60: 4200 | G60: 800 | I60: 0.1111 | J60: 0.67 | K60: 0 | L60: 0.67 | M60: 0.16 | N60: 0
A61: 57 | B61: Will Mallory | C61: IND | D61: JAC | E61: 4300 | G61: 450 | I61: 0.1818 | J61: 1.09 | K61: 1.3 | L61: 1.17 | M61: 0.27 | N61: 0
A62: 58 | B62: Ben Yurosek | C62: MIN | D62: DET | E62: 4000 | G62: 1800 | I62: 0.0526 | J62: 0.32 | K62: 0 | L62: 0.32 | M62: 0.08 | N62: 0
A63: 59 | B63: Nick Muse | C63: ATL | D63: TB | E63: 4100 | G63: 2400 | I63: 0.04 | J63: 0.24 | K63: 0 | L63: 0.24 | M63: 0.06 | N63: 0
A64: 60 | B64: James Mitchell | C64: DAL | D64: ARI | E64: 4000 | I64: 0.0244 | J64: 0 | K64: 0 | L64: 0 | M64: 0 | N64: 0.08
A65: 61 | B65: Brenden Bates | C65: JAC | D65: IND | E65: 4000 | I65: 0.0667 | J65: 0 | K65: 0 | L65: 0 | M65: 0 | N65: 0.08
A66: 62 | B66: Lucas Krull | C66: DEN | D66: KC | E66: 4000 | I66: 0.0345 | J66: 0 | K66: 0 | L66: 0 | M66: 0 | N66: 0.08
A67: 63 | B67: Pharaoh Brown | C67: IND | D67: JAC | E67: 4000 | G67: 1900 | I67: 0.05 | J67: 0.3 | K67: 0 | L67: 0.3 | M67: 0.08 | N67: 0
A68: 64 | B68: Jelani Woods | C68: NYJ | D68: LV | E68: 4200 | G68: 1700 | I68: 0.0556 | J68: 0.33 | K68: 1.5 | L68: 0.8 | M68: 0.19 | N68: 0
A69: 65 | B69: Brock Wright | C69: DET | D69: MIN | E69: 4400 | G69: 1200 | I69: 0.0769 | J69: 0.46 | K69: 0 | L69: 0.46 | M69: 0.1 | N69: 0
A70: 66 | B70: Daniel Bellinger | C70: TEN | D70: CIN | E70: 4300 | G70: 1000 | I70: 0.0909 | J70: 0.55 | K70: 2.2 | L70: 1.21 | M70: 0.28 | N70: 0
A71: 67 | B71: Cam Grandy | C71: MIN | D71: DET | E71: 4000 | I71: 0.0435 | J71: 0 | K71: 0 | L71: 0 | M71: 0 | N71: 0.08
A72: 68 | B72: Hunter Long | C72: ARI | D72: DAL | E72: 4000 | I72: 0.0385 | J72: 0 | K72: 0 | L72: 0 | M72: 0 | N72: 0.08
A73: 69 | B73: Will Kacmarek | C73: MIA | D73: NE | E73: 4300 | G73: 800 | I73: 0.1111 | J73: 0.67 | K73: 1.9 | L73: 1.16 | M73: 0.27 | N73: 0
A74: 70 | B74: Charlie Woerner | C74: ATL | D74: TB | E74: 4000 | G74: 1700 | I74: 0.0556 | J74: 0.33 | K74: 0 | L74: 0.33 | M74: 0.08 | N74: 0
A75: 71 | B75: Robert Tonyan | C75: PIT | D75: CLE | E75: 4000 | G75: 1300 | I75: 0.0714 | J75: 0.43 | K75: 0 | L75: 0.43 | M75: 0.11 | N75: 0
A76: 72 | B76: Drew Ogletree | C76: IND | D76: JAC | E76: 4200 | G76: 1300 | I76: 0.0714 | J76: 0.43 | K76: 0 | L76: 0.43 | M76: 0.1 | N76: 0
A77: 73 | B77: Payne Durham | C77: TB | D77: ATL | E77: 4100 | G77: 1400 | I77: 0.0667 | J77: 0.4 | K77: 0 | L77: 0.4 | M77: 0.1 | N77: 0
A78: 74 | B78: Connor Heyward | C78: LV | D78: NYJ | E78: 4000 | G78: 800 | I78: 0.1111 | J78: 0.67 | K78: 0 | L78: 0.67 | M78: 0.17 | N78: 0
A79: 75 | B79: Adam Trautman | C79: DEN | D79: KC | E79: 4300 | G79: 1000 | I79: 0.0909 | J79: 0.55 | K79: 1.3 | L79: 0.85 | M79: 0.2 | N79: 0
A80: 76 | B80: Jake Briningstool | C80: KC | D80: DEN | E80: 4200 | G80: 1700 | I80: 0.0556 | J80: 0.33 | K80: 0 | L80: 0.33 | M80: 0.08 | N80: 0
A81: 77 | B81: Tyler Conklin | C81: DET | D81: MIN | E81: 4300 | G81: 3000 | I81: 0.0323 | J81: 0.19 | K81: 0 | L81: 0.19 | M81: 0.05 | N81: 0
A82: 78 | B82: Bauer Sharp | C82: TB | D82: ATL | E82: 4000 | G82: 1900 | I82: 0.05 | J82: 0.3 | K82: 0 | L82: 0.3 | M82: 0.08 | N82: 0
A83: 79 | B83: Carter Runyon | C83: LV | D83: NYJ | E83: 4000 | I83: 0.0323 | J83: 0 | K83: 0 | L83: 0 | M83: 0 | N83: 0.08
A84: 80 | B84: Quintin Morris | C84: JAC | D84: IND | E84: 4100 | G84: 1000 | I84: 0.0909 | J84: 0.55 | K84: 0 | L84: 0.55 | M84: 0.13 | N84: 0
A85: 81 | B85: Durham Smythe | C85: BAL | D85: BUF | E85: 4000 | I85: 0.0909 | J85: 0 | K85: 0 | L85: 0 | M85: 0 | N85: 0.08
A86: 82 | B86: Jackson Hawes | C86: BUF | D86: BAL | E86: 4400 | G86: 1100 | I86: 0.0833 | J86: 0.5 | K86: 0 | L86: 0.5 | M86: 0.11 | N86: 0
A87: 83 | B87: Kylen Granson | C87: TEN | D87: CIN | E87: 4100 | G87: 3400 | I87: 0.0286 | J87: 0.17 | K87: 0 | L87: 0.17 | M87: 0.04 | N87: 0
A88: 84 | B88: Jack Endries | C88: CIN | D88: TEN | E88: 4100 | G88: 1100 | I88: 0.0833 | J88: 0.5 | K88: 0 | L88: 0.5 | M88: 0.12 | N88: 0
A89: 85 | B89: Patrick Herbert | C89: LAC | D89: LAR | E89: 4100 | I89: 0.0345 | J89: 0 | K89: 0 | L89: 0 | M89: 0 | N89: 0.08
A90: 86 | B90: Keleki Latu | C90: BUF | D90: BAL | E90: 4200 | G90: 1100 | I90: 0.0833 | J90: 0.5 | K90: 0 | L90: 0.5 | M90: 0.12 | N90: 0
A91: 87 | B91: William Wagner | C91: CIN | D91: TEN | E91: 4100 | I91: 0.0345 | J91: 0 | K91: 0 | L91: 0 | M91: 0 | N91: 0.08
A92: 88 | B92: Riley Nowakowski | C92: PIT | D92: CLE | E92: 4000 | G92: 2400 | I92: 0.04 | J92: 0.24 | K92: 0 | L92: 0.24 | M92: 0.06 | N92: 0
A93: 89 | B93: Danny Pinter | C93: BAL | D93: BUF | E93: 4000 | I93: 0.0435 | J93: 0 | K93: 0 | L93: 0 | M93: 0 | N93: 0.08
A94: 90 | B94: James Winchester | C94: KC | D94: DEN | E94: 4000 | I94: 0.0278 | J94: 0 | K94: 0 | L94: 0 | M94: 0 | N94: 0.08
A95: 91 | B95: Cameron Latu | C95: NE | D95: MIA | E95: 4000 | G95: 1400 | I95: 0.0667 | J95: 0.4 | K95: 0 | L95: 0.4 | M95: 0.1 | N95: 0
A96: 92 | B96: Tanner Koziol | C96: JAC | D96: IND | E96: 4000 | G96: 1300 | I96: 0.0714 | J96: 0.43 | K96: 0 | L96: 0.43 | M96: 0.11 | N96: 0
A97: 93 | B97: Tanner Arkin | C97: NE | D97: MIA | E97: 4000 | G97: 1900 | I97: 0.05 | J97: 0.3 | K97: 0 | L97: 0.3 | M97: 0.08 | N97: 0
A98: 94 | B98: Bernhard Raimann | C98: IND | D98: JAC | E98: 4000 | I98: 0.0278 | J98: 0 | K98: 0 | L98: 0 | M98: 0 | N98: 0.08
A99: 95 | B99: Ko Kieft | C99: TB | D99: ATL | E99: 4000 | G99: 1900 | I99: 0.05 | J99: 0.3 | K99: 0 | L99: 0.3 | M99: 0.08 | N99: 0
A100: 96 | B100: David Martin-Robinson | C100: TEN | D100: CIN | E100: 4000 | G100: 3400 | I100: 0.0286 | J100: 0.17 | K100: 0 | L100: 0.17 | M100: 0.04 | N100: 0
A101: 97 | B101: Max Klare | C101: LAR | D101: LAC | E101: 4000 | G101: 1400 | I101: 0.0667 | J101: 0.4 | K101: 0 | L101: 0.4 | M101: 0.1 | N101: 0
A102: 98 | B102: Mitchell Fraboni | C102: DEN | D102: KC | E102: 4000 | I102: =IF(OR(ISBLANK(G102), NOT(ISNUMBER(G102))), "", IF(G102 < 0, -G102 / (-G102 + 100), 100 / (G102 + 100))) | J102: 0 | K102: 0 | L102: 0 | M102: 0 | N102: 0.08
...

Sheet Defenses (D_ST)
A1: Defense & Special Teams (D/ST) Model
A4: Rank | B4: Team Defense | C4: Team | D4: Opponent | E4: Salary | F4: Opponent Total | G4: Projected Score | H4: Value | I4: Projected Ownership | J4: Value | K4: Projected Ownership
A5: 1 | B5: Vikings | C5: MIN | D5: DET | E5: 4300 | F5: 23 | G5: 7.2 | H5: 1.67 | I5: 0.0116 | J5: 1.86 | K5: 0.019
A6: 2 | B6: Bengals | C6: CIN | D6: TEN | E6: 4800 | F6: 23.25 | G6: 7.11 | H6: 1.48 | I6: 0.0096 | J6: 1.47 | K6: 0.014
A7: 3 | B7: Buccaneers | C7: TB | D7: ATL | E7: 3900 | F7: 23 | G7: 7.2 | H7: 1.85 | I7: 0.0132 | J7: 1.39 | K7: 0.0102
A8: 4 | B8: Steelers | C8: PIT | D8: CLE | E8: 4900 | F8: 19.5 | G8: 8.43 | H8: 1.72 | I8: 0.0165 | J8: 1.57 | K8: 0.0119
A9: 5 | B9: Broncos | C9: DEN | D9: KC | E9: 4100 | F9: 20.75 | G9: 7.99 | H9: 1.95 | I9: 0.0174 | J9: 2.07 | K9: 0.0204
A10: 6 | B10: Chiefs | C10: KC | D10: DEN | E10: 4600 | F10: 20.75 | G10: 7.99 | H10: 1.74 | I10: 0.015 | J10: 1.64 | K10: 0.0133
A11: 7 | B11: Jaguars | C11: JAC | D11: IND | E11: 4700 | F11: 23.25 | G11: 7.11 | H11: 1.51 | I11: 0.0099 | J11: 1.63 | K11: 0.0143
A12: 8 | B12: Patriots | C12: NE | D12: MIA | E12: 5000 | F12: 22.25 | G12: 7.46 | H12: 1.49 | I12: 0.0107 | J12: 1.35 | K12: 0.0096
A13: 9 | B13: Titans | C13: TEN | D13: CIN | E13: 3300 | F13: 23.25 | G13: 7.11 | H13: 2.16 | I13: 0.0157 | J13: 1.78 | K13: 0.0137
A14: 10 | B14: Browns | C14: CLE | D14: PIT | E14: 4200 | F14: 19.5 | G14: 8.43 | H14: 2.01 | I14: 0.0202 | J14: 2.2 | K14: 0.0238
A15: 11 | B15: Falcons | C15: ATL | D15: TB | E15: 3700 | F15: 23 | G15: 7.2 | H15: 1.95 | I15: 0.0141 | J15: 1.86 | K15: 0.017
A16: 12 | B16: Jets | C16: NYJ | D16: LV | E16: 3800 | F16: 22.5 | G16: 7.38 | H16: 1.94 | I16: 0.0148 | J16: 1.83 | K16: 0.0148
... A30: 26 | B30: Dolphins | C30: MIA | D30: NE | E30: 3000 | F30: 22.25 | G30: 7.46 | H30: 2.49 | I30: 0.0208 | J30: 2.33 | K30: 0.0253

Sheet Removed Players
A1: Source Sheet | B1: Position | C1: Player | D1: Team | E1: Original Rank | F1: Removal Reason
A2: Quarterbacks (QB) | B2: QB | C2: Dillon Gabriel | D2: CLE | E2: 28 | F2: Not in top-2 Week 1 depth-chart role
A3: Quarterbacks (QB) | B3: QB | C3: Cooper Rush | D3: ATL | E3: 29 | F3: Not in top-2 Week 1 depth-chart role
A4: Quarterbacks (QB) | B4: QB | C4: J.J. McCarthy | D4: MIN | E4: 30 | F4: Not in top-2 Week 1 depth-chart role
A5: Quarterbacks (QB) | B5: QB | C5: Joey Aguilar | D5: JAC | E5: 32 | F5: Not in top-2 Week 1 depth-chart role
A6: Quarterbacks (QB) | B6: QB | C6: Skylar Thompson | D6: BAL | E6: 34 | F6: Not in top-2 Week 1 depth-chart role
A7: Quarterbacks (QB) | B7: QB | C7: Joe Fagnano | D7: BAL | E7: 36 | F7: Not in top-2 Week 1 depth-chart role
A8: Quarterbacks (QB) | B8: QB | C8: Cam Miller | D8: MIA | E8: 37 | F8: Not in top-2 Week 1 depth-chart role
A9: Quarterbacks (QB) | B9: QB | C9: Cole Payton | D9: PHI | E9: 39 | F9: Not in top-2 Week 1 depth-chart role
A10: Quarterbacks (QB) | B10: QB | C10: Nick Mullens | D10: JAC | E10: 40 | F10: Not in top-2 Week 1 depth-chart role
A11: Quarterbacks (QB) | B11: QB | C11: Sam Hartman | D11: WAS | E11: 42 | F11: Not in top-2 Week 1 depth-chart role
A12: Quarterbacks (QB) | B12: QB | C12: Bailey Zappe | D12: NYJ | E12: 44 | F12: Not in top-2 Week 1 depth-chart role
A13: Quarterbacks (QB) | B13: QB | C13: Drew Allar | D13: PIT | E13: 45 | F13: Not in top-2 Week 1 depth-chart role
... A435: Tight Ends (TE) | B435: TE | C435: Nick Muse | D435: ATL | E435: 168 | F435: Not in top-2 Week 1 depth-chart role
